{
  "Types": [
    {
      "Namespace": "Sandbox.DataModel",
      "Methods": [
        {
          "ReturnType": "System.String",
          "Parameters": [],
          "l": {
            "File": "Systems/Project/ProjectConfig.cs",
            "Line": 177
          },
          "IsPublic": true,
          "FullName": "Sandbox.DataModel.ProjectConfig.ToJson",
          "Name": "ToJson",
          "DeclaringType": "Sandbox.DataModel.ProjectConfig",
          "Attributes": [
            {
              "FullName": "DescriptionAttribute",
              "ConstructorArguments": [
                "Serialize the entire config to a JSON string."
              ]
            },
            {
              "FullName": "Sandbox.Internal.SourceLocationAttribute",
              "ConstructorArguments": [
                "Systems\\Project\\ProjectConfig.cs",
                "174"
              ]
            }
          ],
          "Documentation": {
            "Summary": "Serialize the entire config to a JSON string."
          },
          "DocId": "M:Sandbox.DataModel.ProjectConfig.ToJson"
        },
        {
          "ReturnType": "System.Boolean",
          "Parameters": [
            {
              "Name": "keyname",
              "Type": "System.String"
            },
            {
              "Name": "outvalue",
              "Out": true,
              "Type": "T"
            }
          ],
          "l": {
            "File": "Systems/Project/ProjectConfig.cs",
            "Line": 188
          },
          "IsPublic": true,
          "FullName": "Sandbox.DataModel.ProjectConfig.TryGetMeta",
          "Name": "TryGetMeta",
          "DeclaringType": "Sandbox.DataModel.ProjectConfig",
          "Attributes": [
            {
              "FullName": "DescriptionAttribute",
              "ConstructorArguments": [
                "Try to get a value at given key in <span style=\"color: #4EC9B0;\">ProjectConfig</span>.<span style=\"color: #DCDCDC;\">Metadata</span>."
              ]
            },
            {
              "FullName": "Sandbox.Internal.SourceLocationAttribute",
              "ConstructorArguments": [
                "Systems\\Project\\ProjectConfig.cs",
                "186"
              ]
            }
          ],
          "Documentation": {
            "Summary": "Try to get a value at given key in <see cref=\"P:Sandbox.DataModel.ProjectConfig.Metadata\" />.",
            "Return": "Whether the value was successfully retrieved.",
            "Params": {
              "keyname": "The key to retrieve the value of.",
              "outvalue": "The value, if it was present in the metadata storage."
            },
            "TypeParams": {
              "T": "Type of the value."
            }
          },
          "DocId": "M:Sandbox.DataModel.ProjectConfig.TryGetMeta``1(System.String,``0@)"
        },
        {
          "ReturnType": "T",
          "Parameters": [
            {
              "Name": "keyname",
              "Type": "System.String"
            },
            {
              "Name": "defaultValue",
              "Type": "T"
            }
          ],
          "l": {
            "File": "Systems/Project/ProjectConfig.cs",
            "Line": 223
          },
          "IsPublic": true,
          "FullName": "Sandbox.DataModel.ProjectConfig.GetMetaOrDefault",
          "Name": "GetMetaOrDefault",
          "DeclaringType": "Sandbox.DataModel.ProjectConfig",
          "Attributes": [
            {
              "FullName": "DescriptionAttribute",
              "ConstructorArguments": [
                "Get the package's meta value. If it's missing or the wrong type then use the default value."
              ]
            },
            {
              "FullName": "Sandbox.Internal.SourceLocationAttribute",
              "ConstructorArguments": [
                "Systems\\Project\\ProjectConfig.cs",
                "220"
              ]
            }
          ],
          "Documentation": {
            "Summary": "Get the package's meta value. If it's missing or the wrong type then use the default value."
          },
          "DocId": "M:Sandbox.DataModel.ProjectConfig.GetMetaOrDefault``1(System.String,``0)"
        },
        {
          "ReturnType": "System.Boolean",
          "Parameters": [
            {
              "Name": "keyname",
              "Type": "System.String"
            },
            {
              "Name": "outvalue",
              "Type": "System.Object"
            }
          ],
          "l": {
            "File": "Systems/Project/ProjectConfig.cs",
            "Line": 256
          },
          "IsPublic": true,
          "FullName": "Sandbox.DataModel.ProjectConfig.SetMeta",
          "Name": "SetMeta",
          "DeclaringType": "Sandbox.DataModel.ProjectConfig",
          "Attributes": [
            {
              "FullName": "DescriptionAttribute",
              "ConstructorArguments": [
                "Store custom data at given key in the <span style=\"color: #4EC9B0;\">ProjectConfig</span>.<span style=\"color: #DCDCDC;\">Metadata</span>."
              ]
            },
            {
              "FullName": "Sandbox.Internal.SourceLocationAttribute",
              "ConstructorArguments": [
                "Systems\\Project\\ProjectConfig.cs",
                "254"
              ]
            }
          ],
          "Documentation": {
            "Summary": "Store custom data at given key in the <see cref=\"P:Sandbox.DataModel.ProjectConfig.Metadata\" />.",
            "Return": "Always true.",
            "Params": {
              "keyname": "The key for the data.",
              "outvalue": "The data itself to store."
            }
          },
          "DocId": "M:Sandbox.DataModel.ProjectConfig.SetMeta(System.String,System.Object)"
        }
      ],
      "Constructors": [
        {
          "ReturnType": "System.Void",
          "Parameters": [],
          "l": {
            "File": "Systems/Project/ProjectConfig.cs",
            "Line": 132
          },
          "IsPublic": true,
          "FullName": "Sandbox.DataModel.ProjectConfig..ctor",
          "Name": ".ctor",
          "DeclaringType": "Sandbox.DataModel.ProjectConfig",
          "DocId": "M:Sandbox.DataModel.ProjectConfig.#ctor"
        }
      ],
      "Properties": [
        {
          "PropertyType": "System.IO.DirectoryInfo",
          "Loc": {
            "File": "Systems/Project/ProjectConfig.cs",
            "Line": 20
          },
          "IsPublic": true,
          "FullName": "Sandbox.DataModel.ProjectConfig.Directory",
          "Name": "Directory",
          "Attributes": [
            {
              "FullName": "System.Text.Json.Serialization.JsonIgnoreAttribute"
            },
            {
              "FullName": "Sandbox.HideAttribute"
            },
            {
              "FullName": "DescriptionAttribute",
              "ConstructorArguments": [
                "The directory housing this addon (TODO)"
              ]
            },
            {
              "FullName": "Sandbox.Internal.SourceLocationAttribute",
              "ConstructorArguments": [
                "Systems\\Project\\ProjectConfig.cs",
                "17"
              ]
            }
          ],
          "Documentation": {
            "Summary": "The directory housing this addon (TODO)"
          },
          "DocId": "P:Sandbox.DataModel.ProjectConfig.Directory"
        },
        {
          "PropertyType": "System.IO.DirectoryInfo",
          "Loc": {
            "File": "Systems/Project/ProjectConfig.cs",
            "Line": 27
          },
          "IsPublic": true,
          "FullName": "Sandbox.DataModel.ProjectConfig.AssetsDirectory",
          "Name": "AssetsDirectory",
          "Attributes": [
            {
              "FullName": "System.Text.Json.Serialization.JsonIgnoreAttribute"
            },
            {
              "FullName": "Sandbox.HideAttribute"
            },
            {
              "FullName": "DescriptionAttribute",
              "ConstructorArguments": [
                "The directory housing this addon (TODO)"
              ]
            },
            {
              "FullName": "Sandbox.Internal.SourceLocationAttribute",
              "ConstructorArguments": [
                "Systems\\Project\\ProjectConfig.cs",
                "24"
              ]
            }
          ],
          "Documentation": {
            "Summary": "The directory housing this addon (TODO)"
          },
          "DocId": "P:Sandbox.DataModel.ProjectConfig.AssetsDirectory"
        },
        {
          "PropertyType": "System.String",
          "Loc": {
            "File": "Systems/Project/ProjectConfig.cs",
            "Line": 35
          },
          "IsPublic": true,
          "FullName": "Sandbox.DataModel.ProjectConfig.Title",
          "Name": "Title",
          "Attributes": [
            {
              "FullName": "System.ComponentModel.DataAnnotations.DisplayAttribute"
            },
            {
              "FullName": "System.ComponentModel.DataAnnotations.MaxLengthAttribute",
              "ConstructorArguments": [
                "32"
              ]
            },
            {
              "FullName": "System.ComponentModel.DataAnnotations.MinLengthAttribute",
              "ConstructorArguments": [
                "3"
              ]
            },
            {
              "FullName": "DescriptionAttribute",
              "ConstructorArguments": [
                "The human readable title, for example \"Sandbox\", \"Counter-Strike\""
              ]
            },
            {
              "FullName": "Sandbox.Internal.SourceLocationAttribute",
              "ConstructorArguments": [
                "Systems\\Project\\ProjectConfig.cs",
                "31"
              ]
            }
          ],
          "Documentation": {
            "Summary": "The human readable title, for example \"Sandbox\", \"Counter-Strike\""
          },
          "DocId": "P:Sandbox.DataModel.ProjectConfig.Title"
        },
        {
          "PropertyType": "System.String",
          "Loc": {
            "File": "Systems/Project/ProjectConfig.cs",
            "Line": 41
          },
          "IsPublic": true,
          "FullName": "Sandbox.DataModel.ProjectConfig.Type",
          "Name": "Type",
          "Attributes": [
            {
              "FullName": "System.ComponentModel.DataAnnotations.DisplayAttribute"
            },
            {
              "FullName": "DescriptionAttribute",
              "ConstructorArguments": [
                "The type of addon. Current valid values are \"game\""
              ]
            },
            {
              "FullName": "Sandbox.Internal.SourceLocationAttribute",
              "ConstructorArguments": [
                "Systems\\Project\\ProjectConfig.cs",
                "39"
              ]
            }
          ],
          "Documentation": {
            "Summary": "The type of addon. Current valid values are \"game\""
          },
          "DocId": "P:Sandbox.DataModel.ProjectConfig.Type"
        },
        {
          "PropertyType": "System.String",
          "Loc": {
            "File": "Systems/Project/ProjectConfig.cs",
            "Line": 48
          },
          "IsPublic": true,
          "FullName": "Sandbox.DataModel.ProjectConfig.Org",
          "Name": "Org",
          "Attributes": [
            {
              "FullName": "System.ComponentModel.DataAnnotations.DisplayAttribute"
            },
            {
              "FullName": "EditorAttribute",
              "ConstructorArguments": [
                "organization"
              ]
            },
            {
              "FullName": "DescriptionAttribute",
              "ConstructorArguments": [
                "The ident of the org that owns this addon. For example \"facepunch\", \"valve\"."
              ]
            },
            {
              "FullName": "Sandbox.Internal.SourceLocationAttribute",
              "ConstructorArguments": [
                "Systems\\Project\\ProjectConfig.cs",
                "45"
              ]
            }
          ],
          "Documentation": {
            "Summary": "The ident of the org that owns this addon. For example \"facepunch\", \"valve\"."
          },
          "DocId": "P:Sandbox.DataModel.ProjectConfig.Org"
        },
        {
          "PropertyType": "System.String",
          "Loc": {
            "File": "Systems/Project/ProjectConfig.cs",
            "Line": 57
          },
          "IsPublic": true,
          "FullName": "Sandbox.DataModel.ProjectConfig.Ident",
          "Name": "Ident",
          "Attributes": [
            {
              "FullName": "System.ComponentModel.DataAnnotations.DisplayAttribute"
            },
            {
              "FullName": "System.ComponentModel.DataAnnotations.MaxLengthAttribute",
              "ConstructorArguments": [
                "64"
              ]
            },
            {
              "FullName": "System.ComponentModel.DataAnnotations.MinLengthAttribute",
              "ConstructorArguments": [
                "2"
              ]
            },
            {
              "FullName": "System.ComponentModel.DataAnnotations.RegularExpressionAttribute",
              "ConstructorArguments": [
                "^[a-z0-9_\\-]+$"
              ]
            },
            {
              "FullName": "DescriptionAttribute",
              "ConstructorArguments": [
                "The ident of this addon. For example \"sandbox\", \"cs\" or \"dm98\""
              ]
            },
            {
              "FullName": "Sandbox.Internal.SourceLocationAttribute",
              "ConstructorArguments": [
                "Systems\\Project\\ProjectConfig.cs",
                "52"
              ]
            }
          ],
          "Documentation": {
            "Summary": "The ident of this addon. For example \"sandbox\", \"cs\" or \"dm98\""
          },
          "DocId": "P:Sandbox.DataModel.ProjectConfig.Ident"
        },
        {
          "PropertyType": "Sandbox.Package.Type",
          "Loc": {
            "File": "Systems/Project/ProjectConfig.cs",
            "Line": 64
          },
          "IsPublic": true,
          "FullName": "Sandbox.DataModel.ProjectConfig.PackageType",
          "Name": "PackageType",
          "Attributes": [
            {
              "FullName": "System.Text.Json.Serialization.JsonIgnoreAttribute"
            },
            {
              "FullName": "System.ObsoleteAttribute",
              "ConstructorArguments": [
                "Compare string Type instead"
              ]
            },
            {
              "FullName": "DescriptionAttribute",
              "ConstructorArguments": [
                "Type of the package."
              ]
            },
            {
              "FullName": "Sandbox.Internal.SourceLocationAttribute",
              "ConstructorArguments": [
                "Systems\\Project\\ProjectConfig.cs",
                "61"
              ]
            }
          ],
          "Documentation": {
            "Summary": "Type of the package."
          },
          "DocId": "P:Sandbox.DataModel.ProjectConfig.PackageType"
        },
        {
          "PropertyType": "System.String",
          "Loc": {
            "File": "Systems/Project/ProjectConfig.cs",
            "Line": 71
          },
          "IsPublic": true,
          "FullName": "Sandbox.DataModel.ProjectConfig.FullIdent",
          "Name": "FullIdent",
          "Attributes": [
            {
              "FullName": "Sandbox.HideAttribute"
            },
            {
              "FullName": "System.Text.Json.Serialization.JsonIgnoreAttribute"
            },
            {
              "FullName": "DescriptionAttribute",
              "ConstructorArguments": [
                "Returns a combination of Org and Ident - for example \"facepunch.sandbox\" or \"valve.cs\"."
              ]
            },
            {
              "FullName": "Sandbox.Internal.SourceLocationAttribute",
              "ConstructorArguments": [
                "Systems\\Project\\ProjectConfig.cs",
                "68"
              ]
            }
          ],
          "Documentation": {
            "Summary": "Returns a combination of Org and Ident - for example \"facepunch.sandbox\" or \"valve.cs\"."
          },
          "DocId": "P:Sandbox.DataModel.ProjectConfig.FullIdent"
        },
        {
          "PropertyType": "System.Int32",
          "Loc": {
            "File": "Systems/Project/ProjectConfig.cs",
            "Line": 77
          },
          "IsPublic": true,
          "FullName": "Sandbox.DataModel.ProjectConfig.Schema",
          "Name": "Schema",
          "Attributes": [
            {
              "FullName": "Sandbox.HideAttribute"
            },
            {
              "FullName": "DescriptionAttribute",
              "ConstructorArguments": [
                "The version of the addon file. Allows us to upgrade internally."
              ]
            },
            {
              "FullName": "Sandbox.Internal.SourceLocationAttribute",
              "ConstructorArguments": [
                "Systems\\Project\\ProjectConfig.cs",
                "75"
              ]
            }
          ],
          "Documentation": {
            "Summary": "The version of the addon file. Allows us to upgrade internally."
          },
          "DocId": "P:Sandbox.DataModel.ProjectConfig.Schema"
        },
        {
          "PropertyType": "System.Boolean",
          "Loc": {
            "File": "Systems/Project/ProjectConfig.cs",
            "Line": 83
          },
          "IsPublic": true,
          "FullName": "Sandbox.DataModel.ProjectConfig.IncludeSourceFiles",
          "Name": "IncludeSourceFiles",
          "Attributes": [
            {
              "FullName": "Sandbox.HideAttribute"
            },
            {
              "FullName": "DescriptionAttribute",
              "ConstructorArguments": [
                "If true then we'll include all the source files"
              ]
            },
            {
              "FullName": "Sandbox.Internal.SourceLocationAttribute",
              "ConstructorArguments": [
                "Systems\\Project\\ProjectConfig.cs",
                "81"
              ]
            }
          ],
          "Documentation": {
            "Summary": "If true then we'll include all the source files"
          },
          "DocId": "P:Sandbox.DataModel.ProjectConfig.IncludeSourceFiles"
        },
        {
          "PropertyType": "System.String",
          "Loc": {
            "File": "Systems/Project/ProjectConfig.cs",
            "Line": 88
          },
          "IsPublic": true,
          "FullName": "Sandbox.DataModel.ProjectConfig.Resources",
          "Name": "Resources",
          "Attributes": [
            {
              "FullName": "DescriptionAttribute",
              "ConstructorArguments": [
                "A list of paths in which to look for extra assets to upload with the addon. Note that compiled asset files are automatically included."
              ]
            },
            {
              "FullName": "Sandbox.Internal.SourceLocationAttribute",
              "ConstructorArguments": [
                "Systems\\Project\\ProjectConfig.cs",
                "87"
              ]
            }
          ],
          "Documentation": {
            "Summary": "A list of paths in which to look for extra assets to upload with the addon. Note that compiled asset files are automatically included."
          },
          "DocId": "P:Sandbox.DataModel.ProjectConfig.Resources"
        },
        {
          "PropertyType": "System.Collections.Generic.List`1<System.String>",
          "Loc": {
            "File": "Systems/Project/ProjectConfig.cs",
            "Line": 93
          },
          "IsPublic": true,
          "FullName": "Sandbox.DataModel.ProjectConfig.PackageReferences",
          "Name": "PackageReferences",
          "Attributes": [
            {
              "FullName": "DescriptionAttribute",
              "ConstructorArguments": [
                "A list of packages that this package depends on. These should be installed alongside this package."
              ]
            },
            {
              "FullName": "Sandbox.Internal.SourceLocationAttribute",
              "ConstructorArguments": [
                "Systems\\Project\\ProjectConfig.cs",
                "92"
              ]
            }
          ],
          "Documentation": {
            "Summary": "A list of packages that this package depends on. These should be installed alongside this package."
          },
          "DocId": "P:Sandbox.DataModel.ProjectConfig.PackageReferences"
        },
        {
          "PropertyType": "System.Collections.Generic.List`1<System.String>",
          "Loc": {
            "File": "Systems/Project/ProjectConfig.cs",
            "Line": 100
          },
          "IsPublic": true,
          "FullName": "Sandbox.DataModel.ProjectConfig.EditorReferences",
          "Name": "EditorReferences",
          "Attributes": [
            {
              "FullName": "DescriptionAttribute",
              "ConstructorArguments": [
                "A list of packages that this package uses but there is no need to install. For example, a map package might use a model package - but there is no need to download that model package because any usage will organically be included in the manifest. However, when loading this item in the editor, it'd make sense to install these 'cloud' packages."
              ]
            },
            {
              "FullName": "Sandbox.Internal.SourceLocationAttribute",
              "ConstructorArguments": [
                "Systems\\Project\\ProjectConfig.cs",
                "99"
              ]
            }
          ],
          "Documentation": {
            "Summary": "A list of packages that this package uses but there is no need to install. For example, a map package might use\na model package - but there is no need to download that model package because any usage will organically be included\nin the manifest. However, when loading this item in the editor, it'd make sense to install these 'cloud' packages."
          },
          "DocId": "P:Sandbox.DataModel.ProjectConfig.EditorReferences"
        },
        {
          "PropertyType": "System.Collections.Generic.List`1<System.String>",
          "Loc": {
            "File": "Systems/Project/ProjectConfig.cs",
            "Line": 105
          },
          "IsPublic": true,
          "FullName": "Sandbox.DataModel.ProjectConfig.Mounts",
          "Name": "Mounts",
          "Attributes": [
            {
              "FullName": "DescriptionAttribute",
              "ConstructorArguments": [
                "A list of mounts that are required"
              ]
            },
            {
              "FullName": "Sandbox.Internal.SourceLocationAttribute",
              "ConstructorArguments": [
                "Systems\\Project\\ProjectConfig.cs",
                "104"
              ]
            }
          ],
          "Documentation": {
            "Summary": "A list of mounts that are required"
          },
          "DocId": "P:Sandbox.DataModel.ProjectConfig.Mounts"
        },
        {
          "PropertyType": "System.Boolean",
          "Loc": {
            "File": "Systems/Project/ProjectConfig.cs",
            "Line": 126
          },
          "IsPublic": true,
          "FullName": "Sandbox.DataModel.ProjectConfig.IsStandaloneOnly",
          "Name": "IsStandaloneOnly",
          "Attributes": [
            {
              "FullName": "DescriptionAttribute",
              "ConstructorArguments": [
                "Whether or not this project is standalone-only, and supports disabling the whitelist, compiling with /unsafe, etc."
              ]
            },
            {
              "FullName": "Sandbox.Internal.SourceLocationAttribute",
              "ConstructorArguments": [
                "Systems\\Project\\ProjectConfig.cs",
                "125"
              ]
            }
          ],
          "Documentation": {
            "Summary": "Whether or not this project is standalone-only, and supports disabling the whitelist, compiling with /unsafe, etc."
          },
          "DocId": "P:Sandbox.DataModel.ProjectConfig.IsStandaloneOnly"
        },
        {
          "PropertyType": "System.Collections.Generic.Dictionary`2<System.String,System.Object>",
          "Loc": {
            "File": "Systems/Project/ProjectConfig.cs",
            "Line": 132
          },
          "IsPublic": true,
          "FullName": "Sandbox.DataModel.ProjectConfig.Metadata",
          "Name": "Metadata",
          "Attributes": [
            {
              "FullName": "Sandbox.HideAttribute"
            },
            {
              "FullName": "DescriptionAttribute",
              "ConstructorArguments": [
                "Custom key-value storage for this project."
              ]
            },
            {
              "FullName": "Sandbox.Internal.SourceLocationAttribute",
              "ConstructorArguments": [
                "Systems\\Project\\ProjectConfig.cs",
                "130"
              ]
            }
          ],
          "Documentation": {
            "Summary": "Custom key-value storage for this project."
          },
          "DocId": "P:Sandbox.DataModel.ProjectConfig.Metadata"
        }
      ],
      "IsClass": true,
      "Group": "class",
      "Assembly": "Sandbox.Engine",
      "IsPublic": true,
      "FullName": "Sandbox.DataModel.ProjectConfig",
      "Name": "ProjectConfig",
      "Attributes": [
        {
          "FullName": "ExposeAttribute"
        },
        {
          "FullName": "DescriptionAttribute",
          "ConstructorArguments": [
            "Configuration of a <span style=\"color: #4EC9B0;\">Project</span>."
          ]
        },
        {
          "FullName": "Sandbox.Internal.SourceLocationAttribute",
          "ConstructorArguments": [
            "Systems\\Project\\ProjectConfig.cs",
            "11"
          ]
        }
      ],
      "Documentation": {
        "Summary": "Configuration of a <see cref=\"T:Sandbox.Project\" />."
      },
      "DocId": "T:Sandbox.DataModel.ProjectConfig"
    },
    {
      "Namespace": "Sandbox.Menu",
      "Methods": [
        {
          "ReturnType": "System.TimeSpan",
          "Parameters": [],
          "l": {
            "File": "Game/GameMenu/LoadingProgress.ETA.cs",
            "Line": 8
          },
          "IsPublic": true,
          "FullName": "Sandbox.Menu.LoadingProgress.CalculateETA",
          "Name": "CalculateETA",
          "DeclaringType": "Sandbox.Menu.LoadingProgress",
          "Attributes": [
            {
              "FullName": "System.Runtime.CompilerServices.IsReadOnlyAttribute"
            },
            {
              "FullName": "Sandbox.Internal.SourceLocationAttribute",
              "ConstructorArguments": [
                "Game\\GameMenu\\LoadingProgress.ETA.cs",
                "5"
              ]
            }
          ],
          "DocId": "M:Sandbox.Menu.LoadingProgress.CalculateETA"
        }
      ],
      "Properties": [
        {
          "PropertyType": "System.String",
          "Loc": {
            "File": "Game/GameMenu/LoadingProgress.cs",
            "Line": 6
          },
          "IsPublic": true,
          "FullName": "Sandbox.Menu.LoadingProgress.Title",
          "Name": "Title",
          "Attributes": [
            {
              "FullName": "Sandbox.Internal.SourceLocationAttribute",
              "ConstructorArguments": [
                "Game\\GameMenu\\LoadingProgress.cs",
                "5"
              ]
            }
          ],
          "DocId": "P:Sandbox.Menu.LoadingProgress.Title"
        },
        {
          "PropertyType": "System.Double",
          "Loc": {
            "File": "Game/GameMenu/LoadingProgress.cs",
            "Line": 11
          },
          "IsPublic": true,
          "FullName": "Sandbox.Menu.LoadingProgress.Fraction",
          "Name": "Fraction",
          "Attributes": [
            {
              "FullName": "DescriptionAttribute",
              "ConstructorArguments": [
                "A value between 0 and 1, to show a progress bar"
              ]
            },
            {
              "FullName": "Sandbox.Internal.SourceLocationAttribute",
              "ConstructorArguments": [
                "Game\\GameMenu\\LoadingProgress.cs",
                "10"
              ]
            }
          ],
          "Documentation": {
            "Summary": "A value between 0 and 1, to show a progress bar"
          },
          "DocId": "P:Sandbox.Menu.LoadingProgress.Fraction"
        },
        {
          "PropertyType": "System.Double",
          "Loc": {
            "File": "Game/GameMenu/LoadingProgress.cs",
            "Line": 16
          },
          "IsPublic": true,
          "FullName": "Sandbox.Menu.LoadingProgress.Mbps",
          "Name": "Mbps",
          "Attributes": [
            {
              "FullName": "DescriptionAttribute",
              "ConstructorArguments": [
                "The current transfer rate in Megabits per second. 0 is none."
              ]
            },
            {
              "FullName": "Sandbox.Internal.SourceLocationAttribute",
              "ConstructorArguments": [
                "Game\\GameMenu\\LoadingProgress.cs",
                "15"
              ]
            }
          ],
          "Documentation": {
            "Summary": "The current transfer rate in Megabits per second. 0 is none."
          },
          "DocId": "P:Sandbox.Menu.LoadingProgress.Mbps"
        },
        {
          "PropertyType": "System.Double",
          "Loc": {
            "File": "Game/GameMenu/LoadingProgress.cs",
            "Line": 21
          },
          "IsPublic": true,
          "FullName": "Sandbox.Menu.LoadingProgress.Percent",
          "Name": "Percent",
          "Attributes": [
            {
              "FullName": "DescriptionAttribute",
              "ConstructorArguments": [
                "Delta multipled by 100"
              ]
            },
            {
              "FullName": "Sandbox.Internal.SourceLocationAttribute",
              "ConstructorArguments": [
                "Game\\GameMenu\\LoadingProgress.cs",
                "20"
              ]
            }
          ],
          "Documentation": {
            "Summary": "Delta multipled by 100"
          },
          "DocId": "P:Sandbox.Menu.LoadingProgress.Percent"
        },
        {
          "PropertyType": "System.Double",
          "Loc": {
            "File": "Game/GameMenu/LoadingProgress.cs",
            "Line": 26
          },
          "IsPublic": true,
          "FullName": "Sandbox.Menu.LoadingProgress.TotalSize",
          "Name": "TotalSize",
          "Attributes": [
            {
              "FullName": "DescriptionAttribute",
              "ConstructorArguments": [
                "The total size of what we're trying to download"
              ]
            },
            {
              "FullName": "Sandbox.Internal.SourceLocationAttribute",
              "ConstructorArguments": [
                "Game\\GameMenu\\LoadingProgress.cs",
                "25"
              ]
            }
          ],
          "Documentation": {
            "Summary": "The total size of what we're trying to download"
          },
          "DocId": "P:Sandbox.Menu.LoadingProgress.TotalSize"
        }
      ],
      "IsClass": true,
      "IsSealed": true,
      "IsValueType": true,
      "Group": "struct",
      "Assembly": "Sandbox.Engine",
      "IsPublic": true,
      "FullName": "Sandbox.Menu.LoadingProgress",
      "Name": "LoadingProgress",
      "DocId": "T:Sandbox.Menu.LoadingProgress"
    },
    {
      "Namespace": "Sandbox.ModelEditor",
      "BaseType": "Sandbox.LibraryAttribute",
      "Constructors": [
        {
          "ReturnType": "System.Void",
          "Parameters": [
            {
              "Name": "name",
              "Type": "System.String"
            }
          ],
          "l": {
            "File": "Editor/Hammer/ModelEditorAttributes.cs",
            "Line": 116
          },
          "IsPublic": true,
          "FullName": "Sandbox.ModelEditor.GameDataAttribute..ctor",
          "Name": ".ctor",
          "DeclaringType": "Sandbox.ModelEditor.GameDataAttribute",
          "DocId": "M:Sandbox.ModelEditor.GameDataAttribute.#ctor(System.String)"
        }
      ],
      "Properties": [
        {
          "PropertyType": "System.Boolean",
          "Loc": {
            "File": "Editor/Hammer/ModelEditorAttributes.cs",
            "Line": 114
          },
          "IsPublic": true,
          "FullName": "Sandbox.ModelEditor.GameDataAttribute.AllowMultiple",
          "Name": "AllowMultiple",
          "Attributes": [
            {
              "FullName": "DefaultValueAttribute",
              "ConstructorArguments": [
                "Mono.Cecil.CustomAttributeArgument"
              ]
            },
            {
              "FullName": "DescriptionAttribute",
              "ConstructorArguments": [
                "Indicates that this type compiles as list, rather than a single entry in the model. This will also affect how you retrieve this data via Model.GetData()."
              ]
            },
            {
              "FullName": "Sandbox.Internal.SourceLocationAttribute",
              "ConstructorArguments": [
                "Editor\\Hammer\\ModelEditorAttributes.cs",
                "113"
              ]
            }
          ],
          "Documentation": {
            "Summary": "Indicates that this type compiles as list, rather than a single entry in the model.\nThis will also affect how you retrieve this data via Model.GetData()."
          },
          "DocId": "P:Sandbox.ModelEditor.GameDataAttribute.AllowMultiple"
        }
      ],
      "IsAttribute": true,
      "IsClass": true,
      "Group": "class",
      "Assembly": "Sandbox.Engine",
      "IsPublic": true,
      "FullName": "Sandbox.ModelEditor.GameDataAttribute",
      "Name": "GameDataAttribute",
      "Attributes": [
        {
          "FullName": "System.AttributeUsageAttribute"
        },
        {
          "FullName": "DescriptionAttribute",
          "ConstructorArguments": [
            "Indicates that this class/struct should be available as GenericGameData node in ModelDoc"
          ]
        },
        {
          "FullName": "Sandbox.Internal.SourceLocationAttribute",
          "ConstructorArguments": [
            "Editor\\Hammer\\ModelEditorAttributes.cs",
            "104"
          ]
        }
      ],
      "Documentation": {
        "Summary": "Indicates that this class/struct should be available as GenericGameData node in ModelDoc"
      },
      "DocId": "T:Sandbox.ModelEditor.GameDataAttribute"
    },
    {
      "Namespace": "Sandbox.ModelEditor",
      "BaseType": "Sandbox.ModelEditor.Internal.BaseTransformAttribute",
      "Methods": [
        {
          "ReturnType": "System.Void",
          "IsVirtual": true,
          "Parameters": [
            {
              "Name": "dict",
              "Type": "System.Collections.Generic.Dictionary`2<System.String,System.Object>"
            }
          ],
          "l": {
            "File": "Editor/Hammer/ModelEditorAttributes.cs",
            "Line": 146
          },
          "IsProtected": true,
          "FullName": "Sandbox.ModelEditor.AxisAttribute.AddKeys",
          "Name": "AddKeys",
          "DeclaringType": "Sandbox.ModelEditor.AxisAttribute",
          "Attributes": [
            {
              "FullName": "Sandbox.Internal.SourceLocationAttribute",
              "ConstructorArguments": [
                "Editor\\Hammer\\ModelEditorAttributes.cs",
                "144"
              ]
            }
          ],
          "DocId": "M:Sandbox.ModelEditor.AxisAttribute.AddKeys(System.Collections.Generic.Dictionary`2{System.String,System.Object})"
        }
      ],
      "Constructors": [
        {
          "ReturnType": "System.Void",
          "Parameters": [],
          "l": {
            "File": "Editor/Hammer/ModelEditorAttributes.cs",
            "Line": 141
          },
          "IsPublic": true,
          "FullName": "Sandbox.ModelEditor.AxisAttribute..ctor",
          "Name": ".ctor",
          "DeclaringType": "Sandbox.ModelEditor.AxisAttribute",
          "DocId": "M:Sandbox.ModelEditor.AxisAttribute.#ctor"
        }
      ],
      "Properties": [
        {
          "PropertyType": "System.String",
          "Loc": {
            "File": "Editor/Hammer/ModelEditorAttributes.cs",
            "Line": 134
          },
          "IsPublic": true,
          "FullName": "Sandbox.ModelEditor.AxisAttribute.Enabled",
          "Name": "Enabled",
          "Attributes": [
            {
              "FullName": "DescriptionAttribute",
              "ConstructorArguments": [
                "Internal name of a boolean key that dictates whether this helper should draw or not. If unset, will draw always."
              ]
            },
            {
              "FullName": "Sandbox.Internal.SourceLocationAttribute",
              "ConstructorArguments": [
                "Editor\\Hammer\\ModelEditorAttributes.cs",
                "133"
              ]
            }
          ],
          "Documentation": {
            "Summary": "Internal name of a boolean key that dictates whether this helper should draw or not. If unset, will draw always."
          },
          "DocId": "P:Sandbox.ModelEditor.AxisAttribute.Enabled"
        },
        {
          "PropertyType": "System.Boolean",
          "Loc": {
            "File": "Editor/Hammer/ModelEditorAttributes.cs",
            "Line": 139
          },
          "IsPublic": true,
          "FullName": "Sandbox.ModelEditor.AxisAttribute.ParentLine",
          "Name": "ParentLine",
          "Attributes": [
            {
              "FullName": "DescriptionAttribute",
              "ConstructorArguments": [
                "If set to true, when the node is selected a line will be drawn from the helper to the parent attachment/bone."
              ]
            },
            {
              "FullName": "Sandbox.Internal.SourceLocationAttribute",
              "ConstructorArguments": [
                "Editor\\Hammer\\ModelEditorAttributes.cs",
                "138"
              ]
            }
          ],
          "Documentation": {
            "Summary": "If set to true, when the node is selected a line will be drawn from the helper to the parent attachment/bone."
          },
          "DocId": "P:Sandbox.ModelEditor.AxisAttribute.ParentLine"
        }
      ],
      "IsAttribute": true,
      "IsClass": true,
      "Group": "class",
      "Assembly": "Sandbox.Engine",
      "IsPublic": true,
      "FullName": "Sandbox.ModelEditor.AxisAttribute",
      "Name": "AxisAttribute",
      "Attributes": [
        {
          "FullName": "System.AttributeUsageAttribute"
        },
        {
          "FullName": "DescriptionAttribute",
          "ConstructorArguments": [
            "Draws 3 line axis visualization, which can set up to be manipulated via gizmos. You can have multiple of these."
          ]
        },
        {
          "FullName": "Sandbox.Internal.SourceLocationAttribute",
          "ConstructorArguments": [
            "Editor\\Hammer\\ModelEditorAttributes.cs",
            "127"
          ]
        }
      ],
      "Documentation": {
        "Summary": "Draws 3 line axis visualization, which can set up to be manipulated via gizmos. You can have multiple of these."
      },
      "DocId": "T:Sandbox.ModelEditor.AxisAttribute"
    },
    {
      "Namespace": "Sandbox.ModelEditor",
      "BaseType": "Sandbox.ModelEditor.Internal.BaseTransformAttribute",
      "Methods": [
        {
          "ReturnType": "System.Void",
          "IsVirtual": true,
          "Parameters": [
            {
              "Name": "dict",
              "Type": "System.Collections.Generic.Dictionary`2<System.String,System.Object>"
            }
          ],
          "l": {
            "File": "Editor/Hammer/ModelEditorAttributes.cs",
            "Line": 195
          },
          "IsProtected": true,
          "FullName": "Sandbox.ModelEditor.BoxAttribute.AddKeys",
          "Name": "AddKeys",
          "DeclaringType": "Sandbox.ModelEditor.BoxAttribute",
          "Attributes": [
            {
              "FullName": "Sandbox.Internal.SourceLocationAttribute",
              "ConstructorArguments": [
                "Editor\\Hammer\\ModelEditorAttributes.cs",
                "193"
              ]
            }
          ],
          "DocId": "M:Sandbox.ModelEditor.BoxAttribute.AddKeys(System.Collections.Generic.Dictionary`2{System.String,System.Object})"
        }
      ],
      "Constructors": [
        {
          "ReturnType": "System.Void",
          "Parameters": [
            {
              "Name": "dimensionsKey",
              "Type": "System.String"
            }
          ],
          "l": {
            "File": "Editor/Hammer/ModelEditorAttributes.cs",
            "Line": 178
          },
          "IsPublic": true,
          "FullName": "Sandbox.ModelEditor.BoxAttribute..ctor",
          "Name": ".ctor",
          "DeclaringType": "Sandbox.ModelEditor.BoxAttribute",
          "Documentation": {
            "Summary": "Store the box's dimensions in a single key, acting as (maxs-mins) which assumes the box's center is at the models origin.\nThe box's center can be set up to be movable via \"Origin\" property and rotatable via \"Angles\" property.",
            "Params": {
              "dimensionsKey": "Internal name of a key on the node that will store the dimensions of the box."
            }
          },
          "DocId": "M:Sandbox.ModelEditor.BoxAttribute.#ctor(System.String)"
        },
        {
          "ReturnType": "System.Void",
          "Parameters": [
            {
              "Name": "minsKey",
              "Type": "System.String"
            },
            {
              "Name": "maxsKey",
              "Type": "System.String"
            }
          ],
          "l": {
            "File": "Editor/Hammer/ModelEditorAttributes.cs",
            "Line": 187
          },
          "IsPublic": true,
          "FullName": "Sandbox.ModelEditor.BoxAttribute..ctor",
          "Name": ".ctor",
          "DeclaringType": "Sandbox.ModelEditor.BoxAttribute",
          "Documentation": {
            "Summary": "Store the box's dimensions in 2 keys as Mins and Maxs. This type cannot be rotated.",
            "Params": {
              "minsKey": "Internal name of a key on the node that will store the mins of the box.",
              "maxsKey": "Internal name of a key on the node that will store the maxs of the box."
            }
          },
          "DocId": "M:Sandbox.ModelEditor.BoxAttribute.#ctor(System.String,System.String)"
        }
      ],
      "Properties": [
        {
          "PropertyType": "System.Boolean",
          "Loc": {
            "File": "Editor/Hammer/ModelEditorAttributes.cs",
            "Line": 165
          },
          "IsPublic": true,
          "FullName": "Sandbox.ModelEditor.BoxAttribute.HideSurface",
          "Name": "HideSurface",
          "Attributes": [
            {
              "FullName": "DescriptionAttribute",
              "ConstructorArguments": [
                "If set, the semi-transparent box \"walls\" will not be drawn."
              ]
            },
            {
              "FullName": "Sandbox.Internal.SourceLocationAttribute",
              "ConstructorArguments": [
                "Editor\\Hammer\\ModelEditorAttributes.cs",
                "164"
              ]
            }
          ],
          "Documentation": {
            "Summary": "If set, the semi-transparent box \"walls\" will not be drawn."
          },
          "DocId": "P:Sandbox.ModelEditor.BoxAttribute.HideSurface"
        },
        {
          "PropertyType": "System.Boolean",
          "Loc": {
            "File": "Editor/Hammer/ModelEditorAttributes.cs",
            "Line": 171
          },
          "IsPublic": true,
          "FullName": "Sandbox.ModelEditor.BoxAttribute.ShowGizmos",
          "Name": "ShowGizmos",
          "Attributes": [
            {
              "FullName": "DescriptionAttribute",
              "ConstructorArguments": [
                "If set, gizmos will be shown in transform mode to quickly move/scale the box. For \"dimensions\" box Origin/Angles must be set."
              ]
            },
            {
              "FullName": "Sandbox.Internal.SourceLocationAttribute",
              "ConstructorArguments": [
                "Editor\\Hammer\\ModelEditorAttributes.cs",
                "170"
              ]
            }
          ],
          "Documentation": {
            "Summary": "If set, gizmos will be shown in transform mode to quickly move/scale the box.\nFor \"dimensions\" box Origin/Angles must be set."
          },
          "DocId": "P:Sandbox.ModelEditor.BoxAttribute.ShowGizmos"
        }
      ],
      "IsAttribute": true,
      "IsClass": true,
      "Group": "class",
      "Assembly": "Sandbox.Engine",
      "IsPublic": true,
      "FullName": "Sandbox.ModelEditor.BoxAttribute",
      "Name": "BoxAttribute",
      "Attributes": [
        {
          "FullName": "System.AttributeUsageAttribute"
        },
        {
          "FullName": "DescriptionAttribute",
          "ConstructorArguments": [
            "Draws a box, which can be manipulated via gizmos. You can have multiple of these."
          ]
        },
        {
          "FullName": "Sandbox.Internal.SourceLocationAttribute",
          "ConstructorArguments": [
            "Editor\\Hammer\\ModelEditorAttributes.cs",
            "154"
          ]
        }
      ],
      "Documentation": {
        "Summary": "Draws a box, which can be manipulated via gizmos. You can have multiple of these."
      },
      "DocId": "T:Sandbox.ModelEditor.BoxAttribute"
    },
    {
      "Namespace": "Sandbox.ModelEditor",
      "BaseType": "Sandbox.ModelEditor.Internal.BaseTransformAttribute",
      "Methods": [
        {
          "ReturnType": "System.Void",
          "IsVirtual": true,
          "Parameters": [
            {
              "Name": "dict",
              "Type": "System.Collections.Generic.Dictionary`2<System.String,System.Object>"
            }
          ],
          "l": {
            "File": "Editor/Hammer/ModelEditorAttributes.cs",
            "Line": 226
          },
          "IsProtected": true,
          "FullName": "Sandbox.ModelEditor.SphereAttribute.AddKeys",
          "Name": "AddKeys",
          "DeclaringType": "Sandbox.ModelEditor.SphereAttribute",
          "Attributes": [
            {
              "FullName": "Sandbox.Internal.SourceLocationAttribute",
              "ConstructorArguments": [
                "Editor\\Hammer\\ModelEditorAttributes.cs",
                "224"
              ]
            }
          ],
          "DocId": "M:Sandbox.ModelEditor.SphereAttribute.AddKeys(System.Collections.Generic.Dictionary`2{System.String,System.Object})"
        }
      ],
      "Constructors": [
        {
          "ReturnType": "System.Void",
          "Parameters": [
            {
              "Name": "radiusKey",
              "Type": "System.String"
            },
            {
              "Name": "centerKey",
              "Type": "System.String",
              "Default": ""
            }
          ],
          "l": {
            "File": "Editor/Hammer/ModelEditorAttributes.cs",
            "Line": 219
          },
          "IsPublic": true,
          "FullName": "Sandbox.ModelEditor.SphereAttribute..ctor",
          "Name": ".ctor",
          "DeclaringType": "Sandbox.ModelEditor.SphereAttribute",
          "DocId": "M:Sandbox.ModelEditor.SphereAttribute.#ctor(System.String,System.String)"
        }
      ],
      "Properties": [
        {
          "PropertyType": "System.Boolean",
          "Loc": {
            "File": "Editor/Hammer/ModelEditorAttributes.cs",
            "Line": 217
          },
          "IsPublic": true,
          "FullName": "Sandbox.ModelEditor.SphereAttribute.HideSurface",
          "Name": "HideSurface",
          "Attributes": [
            {
              "FullName": "DescriptionAttribute",
              "ConstructorArguments": [
                "If set, the semi-transparent sphere \"wall\"/surface will not be drawn."
              ]
            },
            {
              "FullName": "Sandbox.Internal.SourceLocationAttribute",
              "ConstructorArguments": [
                "Editor\\Hammer\\ModelEditorAttributes.cs",
                "216"
              ]
            }
          ],
          "Documentation": {
            "Summary": "If set, the semi-transparent sphere \"wall\"/surface will not be drawn."
          },
          "DocId": "P:Sandbox.ModelEditor.SphereAttribute.HideSurface"
        }
      ],
      "IsAttribute": true,
      "IsClass": true,
      "Group": "class",
      "Assembly": "Sandbox.Engine",
      "IsPublic": true,
      "FullName": "Sandbox.ModelEditor.SphereAttribute",
      "Name": "SphereAttribute",
      "Attributes": [
        {
          "FullName": "System.AttributeUsageAttribute"
        },
        {
          "FullName": "DescriptionAttribute",
          "ConstructorArguments": [
            "Draws a sphere, which can be manipulated via gizmos. You can have multiple of these."
          ]
        },
        {
          "FullName": "Sandbox.Internal.SourceLocationAttribute",
          "ConstructorArguments": [
            "Editor\\Hammer\\ModelEditorAttributes.cs",
            "207"
          ]
        }
      ],
      "Documentation": {
        "Summary": "Draws a sphere, which can be manipulated via gizmos. You can have multiple of these."
      },
      "DocId": "T:Sandbox.ModelEditor.SphereAttribute"
    },
    {
      "Namespace": "Sandbox.ModelEditor",
      "BaseType": "Sandbox.ModelEditor.Internal.BaseTransformAttribute",
      "Methods": [
        {
          "ReturnType": "System.Void",
          "IsVirtual": true,
          "Parameters": [
            {
              "Name": "dict",
              "Type": "System.Collections.Generic.Dictionary`2<System.String,System.Object>"
            }
          ],
          "l": {
            "File": "Editor/Hammer/ModelEditorAttributes.cs",
            "Line": 266
          },
          "IsProtected": true,
          "FullName": "Sandbox.ModelEditor.CapsuleAttribute.AddKeys",
          "Name": "AddKeys",
          "DeclaringType": "Sandbox.ModelEditor.CapsuleAttribute",
          "Attributes": [
            {
              "FullName": "Sandbox.Internal.SourceLocationAttribute",
              "ConstructorArguments": [
                "Editor\\Hammer\\ModelEditorAttributes.cs",
                "264"
              ]
            }
          ],
          "DocId": "M:Sandbox.ModelEditor.CapsuleAttribute.AddKeys(System.Collections.Generic.Dictionary`2{System.String,System.Object})"
        }
      ],
      "Constructors": [
        {
          "ReturnType": "System.Void",
          "Parameters": [
            {
              "Name": "point1Key",
              "Type": "System.String"
            },
            {
              "Name": "point2key",
              "Type": "System.String"
            },
            {
              "Name": "radiusKey",
              "Type": "System.String"
            }
          ],
          "l": {
            "File": "Editor/Hammer/ModelEditorAttributes.cs",
            "Line": 247
          },
          "IsPublic": true,
          "FullName": "Sandbox.ModelEditor.CapsuleAttribute..ctor",
          "Name": ".ctor",
          "DeclaringType": "Sandbox.ModelEditor.CapsuleAttribute",
          "Documentation": {
            "Summary": "This variation has 1 radius for both points."
          },
          "DocId": "M:Sandbox.ModelEditor.CapsuleAttribute.#ctor(System.String,System.String,System.String)"
        },
        {
          "ReturnType": "System.Void",
          "Parameters": [
            {
              "Name": "point1Key",
              "Type": "System.String"
            },
            {
              "Name": "point2key",
              "Type": "System.String"
            },
            {
              "Name": "radius1Key",
              "Type": "System.String"
            },
            {
              "Name": "radius2Key",
              "Type": "System.String"
            }
          ],
          "l": {
            "File": "Editor/Hammer/ModelEditorAttributes.cs",
            "Line": 256
          },
          "IsPublic": true,
          "FullName": "Sandbox.ModelEditor.CapsuleAttribute..ctor",
          "Name": ".ctor",
          "DeclaringType": "Sandbox.ModelEditor.CapsuleAttribute",
          "Documentation": {
            "Summary": "This variation has independent radius for each point."
          },
          "DocId": "M:Sandbox.ModelEditor.CapsuleAttribute.#ctor(System.String,System.String,System.String,System.String)"
        }
      ],
      "Properties": [],
      "IsAttribute": true,
      "IsClass": true,
      "Group": "class",
      "Assembly": "Sandbox.Engine",
      "IsPublic": true,
      "FullName": "Sandbox.ModelEditor.CapsuleAttribute",
      "Name": "CapsuleAttribute",
      "Attributes": [
        {
          "FullName": "System.AttributeUsageAttribute"
        },
        {
          "FullName": "DescriptionAttribute",
          "ConstructorArguments": [
            "Draws a capsule, which can be manipulated via gizmos. You can have multiple of these."
          ]
        },
        {
          "FullName": "Sandbox.Internal.SourceLocationAttribute",
          "ConstructorArguments": [
            "Editor\\Hammer\\ModelEditorAttributes.cs",
            "235"
          ]
        }
      ],
      "Documentation": {
        "Summary": "Draws a capsule, which can be manipulated via gizmos. You can have multiple of these."
      },
      "DocId": "T:Sandbox.ModelEditor.CapsuleAttribute"
    }
  ],
  "_metadata": {
    "chunk": 226,
    "items_count": 7
  }
}