{
  "Types": [
    {
      "Namespace": "Sandbox",
      "Methods": [
        {
          "ReturnType": "System.Single",
          "Parameters": [
            {
              "Name": "analog",
              "Type": "Sandbox.InputAnalog"
            }
          ],
          "l": {
            "File": "Systems/Input/Controller/Input.Controller.cs",
            "Line": 55
          },
          "IsPublic": true,
          "IsStatic": true,
          "FullName": "Sandbox.Input.GetAnalog",
          "Name": "GetAnalog",
          "DeclaringType": "Sandbox.Input",
          "Attributes": [
            {
              "FullName": "DescriptionAttribute",
              "ConstructorArguments": [
                "An analog input, when fetched, is between -1 and 1 (0 being default)"
              ]
            },
            {
              "FullName": "Sandbox.Internal.SourceLocationAttribute",
              "ConstructorArguments": [
                "Systems\\Input\\Controller\\Input.Controller.cs",
                "52"
              ]
            }
          ],
          "Documentation": {
            "Summary": "An analog input, when fetched, is between -1 and 1 (0 being default)"
          },
          "DocId": "M:Sandbox.Input.GetAnalog(Sandbox.InputAnalog)"
        },
        {
          "ReturnType": "System.IDisposable",
          "Parameters": [
            {
              "Name": "index",
              "Type": "System.Int32"
            }
          ],
          "l": {
            "File": "Systems/Input/Controller/Input.Controller.cs",
            "Line": 16707566
          },
          "IsPublic": true,
          "IsStatic": true,
          "FullName": "Sandbox.Input.PlayerScope",
          "Name": "PlayerScope",
          "DeclaringType": "Sandbox.Input",
          "Attributes": [
            {
              "FullName": "DescriptionAttribute",
              "ConstructorArguments": [
                "Push a specific player scope to be active"
              ]
            },
            {
              "FullName": "Sandbox.Internal.SourceLocationAttribute",
              "ConstructorArguments": [
                "Systems\\Input\\Controller\\Input.Controller.cs",
                "108"
              ]
            }
          ],
          "Documentation": {
            "Summary": "Push a specific player scope to be active"
          },
          "DocId": "M:Sandbox.Input.PlayerScope(System.Int32)"
        },
        {
          "ReturnType": "System.Boolean",
          "Parameters": [
            {
              "Name": "action",
              "Type": "System.String"
            },
            {
              "Name": "complainOnMissing",
              "Type": "System.Boolean",
              "Default": "True"
            }
          ],
          "l": {
            "File": "Systems/Input/Input.Actions.cs",
            "Line": 64
          },
          "IsPublic": true,
          "IsStatic": true,
          "FullName": "Sandbox.Input.Down",
          "Name": "Down",
          "DeclaringType": "Sandbox.Input",
          "Attributes": [
            {
              "FullName": "Sandbox.ActionGraphNodeAttribute",
              "ConstructorArguments": [
                "input.down"
              ]
            },
            {
              "FullName": "Sandbox.PureAttribute"
            },
            {
              "FullName": "CategoryAttribute",
              "ConstructorArguments": [
                "Input"
              ]
            },
            {
              "FullName": "IconAttribute",
              "ConstructorArguments": [
                "gamepad"
              ]
            },
            {
              "FullName": "DescriptionAttribute",
              "ConstructorArguments": [
                "Action is currently pressed down"
              ]
            },
            {
              "FullName": "Sandbox.Internal.SourceLocationAttribute",
              "ConstructorArguments": [
                "Systems\\Input\\Input.Actions.cs",
                "60"
              ]
            }
          ],
          "Documentation": {
            "Summary": "Action is currently pressed down"
          },
          "DocId": "M:Sandbox.Input.Down(System.String,System.Boolean)"
        },
        {
          "ReturnType": "System.Boolean",
          "Parameters": [
            {
              "Name": "action",
              "Type": "System.String"
            }
          ],
          "l": {
            "File": "Systems/Input/Input.Actions.cs",
            "Line": 101
          },
          "IsPublic": true,
          "IsStatic": true,
          "FullName": "Sandbox.Input.Pressed",
          "Name": "Pressed",
          "DeclaringType": "Sandbox.Input",
          "Attributes": [
            {
              "FullName": "Sandbox.ActionGraphNodeAttribute",
              "ConstructorArguments": [
                "input.pressed"
              ]
            },
            {
              "FullName": "Sandbox.PureAttribute"
            },
            {
              "FullName": "CategoryAttribute",
              "ConstructorArguments": [
                "Input"
              ]
            },
            {
              "FullName": "IconAttribute",
              "ConstructorArguments": [
                "gamepad"
              ]
            },
            {
              "FullName": "DescriptionAttribute",
              "ConstructorArguments": [
                "Action wasn't pressed but now it is"
              ]
            },
            {
              "FullName": "Sandbox.Internal.SourceLocationAttribute",
              "ConstructorArguments": [
                "Systems\\Input\\Input.Actions.cs",
                "97"
              ]
            }
          ],
          "Documentation": {
            "Summary": "Action wasn't pressed but now it is"
          },
          "DocId": "M:Sandbox.Input.Pressed(System.String)"
        },
        {
          "ReturnType": "System.Boolean",
          "Parameters": [
            {
              "Name": "action",
              "Type": "System.String"
            }
          ],
          "l": {
            "File": "Systems/Input/Input.Actions.cs",
            "Line": 112
          },
          "IsPublic": true,
          "IsStatic": true,
          "FullName": "Sandbox.Input.Released",
          "Name": "Released",
          "DeclaringType": "Sandbox.Input",
          "Attributes": [
            {
              "FullName": "Sandbox.ActionGraphNodeAttribute",
              "ConstructorArguments": [
                "input.released"
              ]
            },
            {
              "FullName": "Sandbox.PureAttribute"
            },
            {
              "FullName": "CategoryAttribute",
              "ConstructorArguments": [
                "Input"
              ]
            },
            {
              "FullName": "IconAttribute",
              "ConstructorArguments": [
                "gamepad"
              ]
            },
            {
              "FullName": "DescriptionAttribute",
              "ConstructorArguments": [
                "Action was pressed but now it isn't"
              ]
            },
            {
              "FullName": "Sandbox.Internal.SourceLocationAttribute",
              "ConstructorArguments": [
                "Systems\\Input\\Input.Actions.cs",
                "108"
              ]
            }
          ],
          "Documentation": {
            "Summary": "Action was pressed but now it isn't"
          },
          "DocId": "M:Sandbox.Input.Released(System.String)"
        },
        {
          "ReturnType": "System.Void",
          "Parameters": [
            {
              "Name": "action",
              "Type": "System.String"
            },
            {
              "Name": "down",
              "Type": "System.Boolean"
            }
          ],
          "l": {
            "File": "Systems/Input/Input.Actions.cs",
            "Line": 121
          },
          "IsPublic": true,
          "IsStatic": true,
          "FullName": "Sandbox.Input.SetAction",
          "Name": "SetAction",
          "DeclaringType": "Sandbox.Input",
          "Attributes": [
            {
              "FullName": "Sandbox.Internal.SourceLocationAttribute",
              "ConstructorArguments": [
                "Systems\\Input\\Input.Actions.cs",
                "120"
              ]
            }
          ],
          "Documentation": {},
          "DocId": "M:Sandbox.Input.SetAction(System.String,System.Boolean)"
        },
        {
          "ReturnType": "System.Void",
          "Parameters": [
            {
              "Name": "action",
              "Type": "System.String"
            }
          ],
          "l": {
            "File": "Systems/Input/Input.Actions.cs",
            "Line": 127
          },
          "IsPublic": true,
          "IsStatic": true,
          "FullName": "Sandbox.Input.Clear",
          "Name": "Clear",
          "DeclaringType": "Sandbox.Input",
          "Attributes": [
            {
              "FullName": "DescriptionAttribute",
              "ConstructorArguments": [
                "Remove this action, so it's no longer being pressed."
              ]
            },
            {
              "FullName": "Sandbox.Internal.SourceLocationAttribute",
              "ConstructorArguments": [
                "Systems\\Input\\Input.Actions.cs",
                "126"
              ]
            }
          ],
          "Documentation": {
            "Summary": "Remove this action, so it's no longer being pressed.",
            "Params": {
              "action": ""
            }
          },
          "DocId": "M:Sandbox.Input.Clear(System.String)"
        },
        {
          "ReturnType": "System.Void",
          "Parameters": [],
          "l": {
            "File": "Systems/Input/Input.Actions.cs",
            "Line": 133
          },
          "IsPublic": true,
          "IsStatic": true,
          "FullName": "Sandbox.Input.ClearActions",
          "Name": "ClearActions",
          "DeclaringType": "Sandbox.Input",
          "Attributes": [
            {
              "FullName": "DescriptionAttribute",
              "ConstructorArguments": [
                "Clears the current input actions, so that none of them are active."
              ]
            },
            {
              "FullName": "Sandbox.Internal.SourceLocationAttribute",
              "ConstructorArguments": [
                "Systems\\Input\\Input.Actions.cs",
                "131"
              ]
            }
          ],
          "Documentation": {
            "Summary": "Clears the current input actions, so that none of them are active."
          },
          "DocId": "M:Sandbox.Input.ClearActions"
        },
        {
          "ReturnType": "System.Void",
          "Parameters": [],
          "l": {
            "File": "Systems/Input/Input.Actions.cs",
            "Line": 144
          },
          "IsPublic": true,
          "IsStatic": true,
          "FullName": "Sandbox.Input.ReleaseActions",
          "Name": "ReleaseActions",
          "DeclaringType": "Sandbox.Input",
          "Attributes": [
            {
              "FullName": "DescriptionAttribute",
              "ConstructorArguments": [
                "Clears the current input actions, so that none of them are active. Unlike ClearActions this will unpress the buttons, so they won't be active again until they're pressed again."
              ]
            },
            {
              "FullName": "Sandbox.Internal.SourceLocationAttribute",
              "ConstructorArguments": [
                "Systems\\Input\\Input.Actions.cs",
                "141"
              ]
            }
          ],
          "Documentation": {
            "Summary": "Clears the current input actions, so that none of them are active. Unlike ClearActions\nthis will unpress the buttons, so they won't be active again until they're pressed again."
          },
          "DocId": "M:Sandbox.Input.ReleaseActions"
        },
        {
          "ReturnType": "System.Void",
          "Parameters": [
            {
              "Name": "name",
              "Type": "System.String"
            }
          ],
          "l": {
            "File": "Systems/Input/Input.Actions.cs",
            "Line": 157
          },
          "IsPublic": true,
          "IsStatic": true,
          "FullName": "Sandbox.Input.ReleaseAction",
          "Name": "ReleaseAction",
          "DeclaringType": "Sandbox.Input",
          "Attributes": [
            {
              "FullName": "DescriptionAttribute",
              "ConstructorArguments": [
                "Releases the action, and it won't be active again until it's pressed again."
              ]
            },
            {
              "FullName": "Sandbox.Internal.SourceLocationAttribute",
              "ConstructorArguments": [
                "Systems\\Input\\Input.Actions.cs",
                "154"
              ]
            }
          ],
          "Documentation": {
            "Summary": "Releases the action, and it won't be active again until it's pressed again."
          },
          "DocId": "M:Sandbox.Input.ReleaseAction(System.String)"
        },
        {
          "ReturnType": "System.Collections.Generic.IEnumerable`1<Sandbox.InputAction>",
          "Parameters": [],
          "l": {
            "File": "Systems/Input/Input.Actions.cs",
            "Line": 288
          },
          "IsPublic": true,
          "IsStatic": true,
          "FullName": "Sandbox.Input.GetActions",
          "Name": "GetActions",
          "DeclaringType": "Sandbox.Input",
          "Attributes": [
            {
              "FullName": "DescriptionAttribute",
              "ConstructorArguments": [
                "Copies all input actions to be used publicly"
              ]
            },
            {
              "FullName": "Sandbox.Internal.SourceLocationAttribute",
              "ConstructorArguments": [
                "Systems\\Input\\Input.Actions.cs",
                "287"
              ]
            }
          ],
          "Documentation": {
            "Summary": "Copies all input actions to be used publicly",
            "Return": ""
          },
          "DocId": "M:Sandbox.Input.GetActions"
        },
        {
          "ReturnType": "System.String",
          "Parameters": [
            {
              "Name": "action",
              "Type": "System.String"
            }
          ],
          "l": {
            "File": "Systems/Input/Input.Actions.cs",
            "Line": 299
          },
          "IsPublic": true,
          "IsStatic": true,
          "FullName": "Sandbox.Input.GetGroupName",
          "Name": "GetGroupName",
          "DeclaringType": "Sandbox.Input",
          "Attributes": [
            {
              "FullName": "DescriptionAttribute",
              "ConstructorArguments": [
                "Finds the <span style=\"color: #4EC9B0;\">InputAction</span>.<span style=\"color: #DCDCDC;\">GroupName</span> of the given action."
              ]
            },
            {
              "FullName": "Sandbox.Internal.SourceLocationAttribute",
              "ConstructorArguments": [
                "Systems\\Input\\Input.Actions.cs",
                "298"
              ]
            }
          ],
          "Documentation": {
            "Summary": "Finds the <see cref=\"P:Sandbox.InputAction.GroupName\" /> of the given action.",
            "Params": {
              "action": "Action name to find the group name of."
            }
          },
          "DocId": "M:Sandbox.Input.GetGroupName(System.String)"
        },
        {
          "ReturnType": "System.String",
          "Parameters": [
            {
              "Name": "name",
              "Type": "System.String"
            },
            {
              "Name": "ignoreController",
              "Type": "System.Boolean",
              "Default": "False"
            }
          ],
          "l": {
            "File": "Systems/Input/Input.cs",
            "Line": 16707566
          },
          "IsPublic": true,
          "IsStatic": true,
          "FullName": "Sandbox.Input.GetButtonOrigin",
          "Name": "GetButtonOrigin",
          "DeclaringType": "Sandbox.Input",
          "Attributes": [
            {
              "FullName": "DescriptionAttribute",
              "ConstructorArguments": [
                "Returns the name of a key bound to this InputAction <example>For example: <pre style=\"color: #DCDCDC; background-color: #111111;\"><code>Input.GetButtonOrigin( \"Undo\" )</code></pre> could return <code style=\"color: #DCDCDC; background-color: #111111; padding: 4px;\">SPACE</code> if using keyboard or <code style=\"color: #DCDCDC; background-color: #111111; padding: 4px;\">A Button</code> when using a controller. </example>"
              ]
            },
            {
              "FullName": "Sandbox.Internal.SourceLocationAttribute",
              "ConstructorArguments": [
                "Systems\\Input\\Input.cs",
                "172"
              ]
            }
          ],
          "Documentation": {
            "Summary": "Returns the name of a key bound to this InputAction\n<example>For example:\n<code>Input.GetButtonOrigin( \"Undo\" )</code>\ncould return <c>SPACE</c> if using keyboard or <c>A Button</c> when using a controller.\n</example>"
          },
          "DocId": "M:Sandbox.Input.GetButtonOrigin(System.String,System.Boolean)"
        },
        {
          "ReturnType": "Sandbox.Texture",
          "Parameters": [
            {
              "Name": "name",
              "Type": "System.String"
            },
            {
              "Name": "size",
              "Type": "Sandbox.InputGlyphSize",
              "Default": "0"
            },
            {
              "Name": "outline",
              "Type": "System.Boolean",
              "Default": "False"
            }
          ],
          "l": {
            "File": "Systems/Input/Input.Glyphs.cs",
            "Line": 16707566
          },
          "IsPublic": true,
          "IsStatic": true,
          "FullName": "Sandbox.Input.GetGlyph",
          "Name": "GetGlyph",
          "DeclaringType": "Sandbox.Input",
          "Attributes": [
            {
              "FullName": "DescriptionAttribute",
              "ConstructorArguments": [
                "Get a glyph texture from the controller bound to the action. If no binding is found will return an 'UNBOUND' glyph."
              ]
            },
            {
              "FullName": "Sandbox.Internal.SourceLocationAttribute",
              "ConstructorArguments": [
                "Systems\\Input\\Input.Glyphs.cs",
                "82"
              ]
            }
          ],
          "Documentation": {
            "Summary": "Get a glyph texture from the controller bound to the action.\nIf no binding is found will return an 'UNBOUND' glyph.",
            "Remarks": "You should update your UI with this every frame, it's very cheap to call and context can change."
          },
          "DocId": "M:Sandbox.Input.GetGlyph(System.String,Sandbox.InputGlyphSize,System.Boolean)"
        },
        {
          "ReturnType": "Sandbox.Texture",
          "Parameters": [
            {
              "Name": "name",
              "Type": "System.String"
            },
            {
              "Name": "size",
              "Type": "Sandbox.InputGlyphSize",
              "Default": "0"
            },
            {
              "Name": "style",
              "Type": "Sandbox.GlyphStyle",
              "Default": "null"
            }
          ],
          "l": {
            "File": "Systems/Input/Input.Glyphs.cs",
            "Line": 119
          },
          "IsPublic": true,
          "IsStatic": true,
          "FullName": "Sandbox.Input.GetGlyph",
          "Name": "GetGlyph",
          "DeclaringType": "Sandbox.Input",
          "Attributes": [
            {
              "FullName": "Sandbox.Internal.SourceLocationAttribute",
              "ConstructorArguments": [
                "Systems\\Input\\Input.Glyphs.cs",
                "116"
              ]
            }
          ],
          "Documentation": {},
          "DocId": "M:Sandbox.Input.GetGlyph(System.String,Sandbox.InputGlyphSize,Sandbox.GlyphStyle)"
        },
        {
          "ReturnType": "Sandbox.Texture",
          "Parameters": [
            {
              "Name": "analog",
              "Type": "Sandbox.InputAnalog"
            },
            {
              "Name": "size",
              "Type": "Sandbox.InputGlyphSize",
              "Default": "0"
            },
            {
              "Name": "outline",
              "Type": "System.Boolean",
              "Default": "False"
            }
          ],
          "l": {
            "File": "Systems/Input/Input.Glyphs.cs",
            "Line": 127
          },
          "IsPublic": true,
          "IsStatic": true,
          "FullName": "Sandbox.Input.GetGlyph",
          "Name": "GetGlyph",
          "DeclaringType": "Sandbox.Input",
          "Attributes": [
            {
              "FullName": "DescriptionAttribute",
              "ConstructorArguments": [
                "Get a glyph texture from an analog input on a controller."
              ]
            },
            {
              "FullName": "Sandbox.Internal.SourceLocationAttribute",
              "ConstructorArguments": [
                "Systems\\Input\\Input.Glyphs.cs",
                "124"
              ]
            }
          ],
          "Documentation": {
            "Summary": "Get a glyph texture from an analog input on a controller."
          },
          "DocId": "M:Sandbox.Input.GetGlyph(Sandbox.InputAnalog,Sandbox.InputGlyphSize,System.Boolean)"
        },
        {
          "ReturnType": "System.String",
          "Parameters": [
            {
              "Name": "analog",
              "Type": "Sandbox.InputAnalog"
            }
          ],
          "l": {
            "File": "Systems/Input/Input.Glyphs.cs",
            "Line": 140
          },
          "IsPublic": true,
          "IsStatic": true,
          "FullName": "Sandbox.Input.GetButtonOrigin",
          "Name": "GetButtonOrigin",
          "DeclaringType": "Sandbox.Input",
          "Attributes": [
            {
              "FullName": "DescriptionAttribute",
              "ConstructorArguments": [
                "Returns the name of the analog axis bound to this <span style=\"color: #86C691;\">InputAnalog</span>. <example>For example: <pre style=\"color: #DCDCDC; background-color: #111111;\"><code>Input.GetButtonOrigin( InputAnalog.Move )</code></pre> could return <code style=\"color: #DCDCDC; background-color: #111111; padding: 4px;\">Left Joystick</code></example>"
              ]
            },
            {
              "FullName": "Sandbox.Internal.SourceLocationAttribute",
              "ConstructorArguments": [
                "Systems\\Input\\Input.Glyphs.cs",
                "136"
              ]
            }
          ],
          "Documentation": {
            "Summary": "Returns the name of the analog axis bound to this <see cref=\"T:Sandbox.InputAnalog\" />.\n<example>For example:\n<code>Input.GetButtonOrigin( InputAnalog.Move )</code>\ncould return <c>Left Joystick</c></example>"
          },
          "DocId": "M:Sandbox.Input.GetButtonOrigin(Sandbox.InputAnalog)"
        },
        {
          "ReturnType": "System.Void",
          "Parameters": [
            {
              "Name": "leftMotor",
              "Type": "System.Single"
            },
            {
              "Name": "rightMotor",
              "Type": "System.Single"
            },
            {
              "Name": "leftTrigger",
              "Type": "System.Single",
              "Default": "0"
            },
            {
              "Name": "rightTrigger",
              "Type": "System.Single",
              "Default": "0"
            },
            {
              "Name": "duration",
              "Type": "System.Int32",
              "Default": "500"
            }
          ],
          "l": {
            "File": "Systems/Input/Input.Haptics.cs",
            "Line": 19
          },
          "IsPublic": true,
          "IsStatic": true,
          "FullName": "Sandbox.Input.TriggerHaptics",
          "Name": "TriggerHaptics",
          "DeclaringType": "Sandbox.Input",
          "Attributes": [
            {
              "FullName": "DescriptionAttribute",
              "ConstructorArguments": [
                "Trigger a haptic event on supported controllers including Xbox trigger impulse rumble."
              ]
            },
            {
              "FullName": "Sandbox.Internal.SourceLocationAttribute",
              "ConstructorArguments": [
                "Systems\\Input\\Input.Haptics.cs",
                "16"
              ]
            }
          ],
          "Documentation": {
            "Summary": "Trigger a haptic event on supported controllers including Xbox trigger impulse rumble.",
            "Remarks": "SDL will translate these commands into haptic pulses that should work on all controller types.",
            "Params": {
              "leftMotor": "The speed of the left motor, between 0.0 and 1.0.",
              "rightMotor": "The speed of the right motor, between 0.0 and 1.0.",
              "leftTrigger": "(Xbox One controller only) The speed of the left trigger motor, between 0.0 and 1.0.",
              "rightTrigger": "(Xbox One controller only) The speed of the right trigger motor, between 0.0 and 1.0.",
              "duration": "How long (in milliseconds) should we apply this for?"
            }
          },
          "DocId": "M:Sandbox.Input.TriggerHaptics(System.Single,System.Single,System.Single,System.Single,System.Int32)"
        },
        {
          "ReturnType": "System.Void",
          "Parameters": [
            {
              "Name": "pattern",
              "Type": "Sandbox.HapticEffect"
            },
            {
              "Name": "lengthScale",
              "Type": "System.Single",
              "Default": "1"
            },
            {
              "Name": "frequencyScale",
              "Type": "System.Single",
              "Default": "1"
            },
            {
              "Name": "amplitudeScale",
              "Type": "System.Single",
              "Default": "1"
            }
          ],
          "l": {
            "File": "Systems/Input/Input.Haptics.cs",
            "Line": 48
          },
          "IsPublic": true,
          "IsStatic": true,
          "FullName": "Sandbox.Input.TriggerHaptics",
          "Name": "TriggerHaptics",
          "DeclaringType": "Sandbox.Input",
          "Attributes": [
            {
              "FullName": "DescriptionAttribute",
              "ConstructorArguments": [
                "Trigger haptics based on a predefined <span style=\"color: #4EC9B0;\">HapticEffect</span>. All <span style=\"color: #4EC9B0;\">HapticEffect</span>s are normalized (start at 0, peak at 1)."
              ]
            },
            {
              "FullName": "Sandbox.Internal.SourceLocationAttribute",
              "ConstructorArguments": [
                "Systems\\Input\\Input.Haptics.cs",
                "45"
              ]
            }
          ],
          "Documentation": {
            "Summary": "Trigger haptics based on a predefined <see cref=\"T:Sandbox.HapticEffect\" />.\nAll <see cref=\"T:Sandbox.HapticEffect\" />s are normalized (start at 0, peak at 1).",
            "Params": {
              "pattern": "The pattern to use",
              "lengthScale": "The amount to scale the pattern's length by.",
              "frequencyScale": "The amount to scale the pattern's frequency by.",
              "amplitudeScale": "The amount to scale the pattern's amplitude by."
            }
          },
          "DocId": "M:Sandbox.Input.TriggerHaptics(Sandbox.HapticEffect,System.Single,System.Single,System.Single)"
        },
        {
          "ReturnType": "System.Void",
          "Parameters": [
            {
              "Name": "pattern",
              "Type": "Sandbox.HapticEffect"
            },
            {
              "Name": "frequencyScale",
              "Type": "System.Single"
            },
            {
              "Name": "amplitudeScale",
              "Type": "System.Single"
            }
          ],
          "l": {
            "File": "Systems/Input/Input.Haptics.cs",
            "Line": 63
          },
          "IsPublic": true,
          "IsStatic": true,
          "FullName": "Sandbox.Input.TriggerHaptics",
          "Name": "TriggerHaptics",
          "DeclaringType": "Sandbox.Input",
          "Attributes": [
            {
              "FullName": "DescriptionAttribute",
              "ConstructorArguments": [
                "Trigger haptics based on a predefined <span style=\"color: #4EC9B0;\">HapticEffect</span>. All <span style=\"color: #4EC9B0;\">HapticEffect</span>s are normalized (start at 0, peak at 1)."
              ]
            },
            {
              "FullName": "Sandbox.Internal.SourceLocationAttribute",
              "ConstructorArguments": [
                "Systems\\Input\\Input.Haptics.cs",
                "60"
              ]
            }
          ],
          "Documentation": {
            "Summary": "Trigger haptics based on a predefined <see cref=\"T:Sandbox.HapticEffect\" />.\nAll <see cref=\"T:Sandbox.HapticEffect\" />s are normalized (start at 0, peak at 1).",
            "Params": {
              "pattern": "The pattern to use",
              "frequencyScale": "The amount to scale the pattern's frequency by.",
              "amplitudeScale": "The amount to scale the pattern's amplitude by."
            }
          },
          "DocId": "M:Sandbox.Input.TriggerHaptics(Sandbox.HapticEffect,System.Single,System.Single)"
        },
        {
          "ReturnType": "System.Void",
          "Parameters": [],
          "l": {
            "File": "Systems/Input/Input.Haptics.cs",
            "Line": 74
          },
          "IsPublic": true,
          "IsStatic": true,
          "FullName": "Sandbox.Input.StopAllHaptics",
          "Name": "StopAllHaptics",
          "DeclaringType": "Sandbox.Input",
          "Attributes": [
            {
              "FullName": "DescriptionAttribute",
              "ConstructorArguments": [
                "Stop all vibration events on the current controller."
              ]
            },
            {
              "FullName": "Sandbox.Internal.SourceLocationAttribute",
              "ConstructorArguments": [
                "Systems\\Input\\Input.Haptics.cs",
                "71"
              ]
            }
          ],
          "Documentation": {
            "Summary": "Stop all vibration events on the current controller."
          },
          "DocId": "M:Sandbox.Input.StopAllHaptics"
        }
      ],
      "Properties": [
        {
          "PropertyType": "System.Int32",
          "Loc": {
            "File": "Systems/Input/Controller/Input.Controller.cs",
            "Line": 18
          },
          "IsPublic": true,
          "IsStatic": true,
          "FullName": "Sandbox.Input.ControllerCount",
          "Name": "ControllerCount",
          "Attributes": [
            {
              "FullName": "DescriptionAttribute",
              "ConstructorArguments": [
                "How many controllers are active right now?"
              ]
            },
            {
              "FullName": "Sandbox.Internal.SourceLocationAttribute",
              "ConstructorArguments": [
                "Systems\\Input\\Controller\\Input.Controller.cs",
                "17"
              ]
            }
          ],
          "Documentation": {
            "Summary": "How many controllers are active right now?"
          },
          "DocId": "P:Sandbox.Input.ControllerCount"
        },
        {
          "PropertyType": "System.Boolean",
          "Loc": {
            "File": "Systems/Input/Controller/Input.Controller.cs",
            "Line": 23
          },
          "IsPublic": true,
          "IsStatic": true,
          "FullName": "Sandbox.Input.EnableVirtualCursor",
          "Name": "EnableVirtualCursor",
          "Attributes": [
            {
              "FullName": "DefaultValueAttribute",
              "ConstructorArguments": [
                "Mono.Cecil.CustomAttributeArgument"
              ]
            },
            {
              "FullName": "DescriptionAttribute",
              "ConstructorArguments": [
                "Whether or not the Virtual Cursor should show when using a controller. Disable this to control the cursor manually."
              ]
            },
            {
              "FullName": "Sandbox.Internal.SourceLocationAttribute",
              "ConstructorArguments": [
                "Systems\\Input\\Controller\\Input.Controller.cs",
                "22"
              ]
            }
          ],
          "Documentation": {
            "Summary": "Whether or not the Virtual Cursor should show when using a controller. Disable this to control the cursor manually."
          },
          "DocId": "P:Sandbox.Input.EnableVirtualCursor"
        },
        {
          "PropertyType": "System.Boolean",
          "Loc": {
            "File": "Systems/Input/Input.Actions.cs",
            "Line": 12
          },
          "IsPublic": true,
          "IsStatic": true,
          "FullName": "Sandbox.Input.UsingController",
          "Name": "UsingController",
          "Attributes": [
            {
              "FullName": "DefaultValueAttribute",
              "ConstructorArguments": [
                "Mono.Cecil.CustomAttributeArgument"
              ]
            },
            {
              "FullName": "DescriptionAttribute",
              "ConstructorArguments": [
                "Was the last button pressed a game controller button?"
              ]
            },
            {
              "FullName": "Sandbox.Internal.SourceLocationAttribute",
              "ConstructorArguments": [
                "Systems\\Input\\Input.Actions.cs",
                "11"
              ]
            }
          ],
          "Documentation": {
            "Summary": "Was the last button pressed a game controller button?"
          },
          "DocId": "P:Sandbox.Input.UsingController"
        },
        {
          "PropertyType": "System.Boolean",
          "Loc": {
            "File": "Systems/Input/Input.Actions.cs",
            "Line": 55
          },
          "IsPublic": true,
          "IsStatic": true,
          "FullName": "Sandbox.Input.EscapePressed",
          "Name": "EscapePressed",
          "Attributes": [
            {
              "FullName": "DescriptionAttribute",
              "ConstructorArguments": [
                "True if escape was pressed"
              ]
            },
            {
              "FullName": "Sandbox.Internal.SourceLocationAttribute",
              "ConstructorArguments": [
                "Systems\\Input\\Input.Actions.cs",
                "51"
              ]
            }
          ],
          "Documentation": {
            "Summary": "True if escape was pressed"
          },
          "DocId": "P:Sandbox.Input.EscapePressed"
        },
        {
          "PropertyType": "System.Collections.Generic.IEnumerable`1<System.String>",
          "Loc": {
            "File": "Systems/Input/Input.Actions.cs",
            "Line": 293
          },
          "IsPublic": true,
          "IsStatic": true,
          "FullName": "Sandbox.Input.ActionNames",
          "Name": "ActionNames",
          "Attributes": [
            {
              "FullName": "DescriptionAttribute",
              "ConstructorArguments": [
                "Names of all actions from the current game's input settings."
              ]
            },
            {
              "FullName": "Sandbox.Internal.SourceLocationAttribute",
              "ConstructorArguments": [
                "Systems\\Input\\Input.Actions.cs",
                "292"
              ]
            }
          ],
          "Documentation": {
            "Summary": "Names of all actions from the current game's input settings."
          },
          "DocId": "P:Sandbox.Input.ActionNames"
        },
        {
          "PropertyType": "System.Boolean",
          "Loc": {
            "File": "Systems/Input/Input.Context.cs",
            "Line": 47
          },
          "IsPublic": true,
          "IsStatic": true,
          "FullName": "Sandbox.Input.Suppressed",
          "Name": "Suppressed",
          "Attributes": [
            {
              "FullName": "DescriptionAttribute",
              "ConstructorArguments": [
                "If the input is suppressed then everything will act like there is no input"
              ]
            },
            {
              "FullName": "Sandbox.Internal.SourceLocationAttribute",
              "ConstructorArguments": [
                "Systems\\Input\\Input.Context.cs",
                "46"
              ]
            }
          ],
          "Documentation": {
            "Summary": "If the input is suppressed then everything will act like there is no input"
          },
          "DocId": "P:Sandbox.Input.Suppressed"
        },
        {
          "PropertyType": "Sandbox.VR.VRInput",
          "Loc": {
            "File": "Systems/Input/Input.cs",
            "Line": 15
          },
          "IsPublic": true,
          "IsStatic": true,
          "FullName": "Sandbox.Input.VR",
          "Name": "VR",
          "Attributes": [
            {
              "FullName": "DescriptionAttribute",
              "ConstructorArguments": [
                "Virtual Reality specific input data."
              ]
            },
            {
              "FullName": "Sandbox.Internal.SourceLocationAttribute",
              "ConstructorArguments": [
                "Systems\\Input\\Input.cs",
                "14"
              ]
            }
          ],
          "Documentation": {
            "Summary": "Virtual Reality specific input data."
          },
          "DocId": "P:Sandbox.Input.VR"
        },
        {
          "PropertyType": "Vector2",
          "Loc": {
            "File": "Systems/Input/Input.cs",
            "Line": 23
          },
          "IsPublic": true,
          "IsStatic": true,
          "FullName": "Sandbox.Input.MouseDelta",
          "Name": "MouseDelta",
          "Attributes": [
            {
              "FullName": "DescriptionAttribute",
              "ConstructorArguments": [
                "Movement delta from the mouse."
              ]
            },
            {
              "FullName": "Sandbox.Internal.SourceLocationAttribute",
              "ConstructorArguments": [
                "Systems\\Input\\Input.cs",
                "19"
              ]
            }
          ],
          "Documentation": {
            "Summary": "Movement delta from the mouse."
          },
          "DocId": "P:Sandbox.Input.MouseDelta"
        },
        {
          "PropertyType": "Vector2",
          "Loc": {
            "File": "Systems/Input/Input.cs",
            "Line": 32
          },
          "IsPublic": true,
          "IsStatic": true,
          "FullName": "Sandbox.Input.MouseWheel",
          "Name": "MouseWheel",
          "Attributes": [
            {
              "FullName": "DescriptionAttribute",
              "ConstructorArguments": [
                "The state of the mouse wheel."
              ]
            },
            {
              "FullName": "Sandbox.Internal.SourceLocationAttribute",
              "ConstructorArguments": [
                "Systems\\Input\\Input.cs",
                "28"
              ]
            }
          ],
          "Documentation": {
            "Summary": "The state of the mouse wheel."
          },
          "DocId": "P:Sandbox.Input.MouseWheel"
        },
        {
          "PropertyType": "System.Boolean",
          "Loc": {
            "File": "Systems/Input/Input.cs",
            "Line": 40
          },
          "IsPublic": true,
          "IsStatic": true,
          "FullName": "Sandbox.Input.MouseCursorVisible",
          "Name": "MouseCursorVisible",
          "Attributes": [
            {
              "FullName": "DescriptionAttribute",
              "ConstructorArguments": [
                "True if the mouse cursor is visible (using UI etc)"
              ]
            },
            {
              "FullName": "Sandbox.Internal.SourceLocationAttribute",
              "ConstructorArguments": [
                "Systems\\Input\\Input.cs",
                "37"
              ]
            }
          ],
          "Documentation": {
            "Summary": "True if the mouse cursor is visible (using UI etc)"
          },
          "DocId": "P:Sandbox.Input.MouseCursorVisible"
        },
        {
          "PropertyType": "Angles",
          "Loc": {
            "File": "Systems/Input/Input.cs",
            "Line": 52
          },
          "IsPublic": true,
          "IsStatic": true,
          "FullName": "Sandbox.Input.AnalogLook",
          "Name": "AnalogLook",
          "Attributes": [
            {
              "FullName": "Sandbox.ActionGraphNodeAttribute",
              "ConstructorArguments": [
                "input.analog.look"
              ]
            },
            {
              "FullName": "CategoryAttribute",
              "ConstructorArguments": [
                "Input"
              ]
            },
            {
              "FullName": "IconAttribute",
              "ConstructorArguments": [
                "gamepad"
              ]
            },
            {
              "FullName": "DescriptionAttribute",
              "ConstructorArguments": [
                "Analog look value from the default input device. This is scaled by Preferences.Sensitivity - so you don't need to scale it afterwards."
              ]
            },
            {
              "FullName": "Sandbox.Internal.SourceLocationAttribute",
              "ConstructorArguments": [
                "Systems\\Input\\Input.cs",
                "47"
              ]
            }
          ],
          "Documentation": {
            "Summary": "Analog look value from the default input device. This is scaled by Preferences.Sensitivity - so you don't need to scale it afterwards."
          },
          "DocId": "P:Sandbox.Input.AnalogLook"
        },
        {
          "PropertyType": "Vector3",
          "Loc": {
            "File": "Systems/Input/Input.cs",
            "Line": 64
          },
          "IsPublic": true,
          "IsStatic": true,
          "FullName": "Sandbox.Input.AnalogMove",
          "Name": "AnalogMove",
          "Attributes": [
            {
              "FullName": "Sandbox.ActionGraphNodeAttribute",
              "ConstructorArguments": [
                "input.analog.move"
              ]
            },
            {
              "FullName": "CategoryAttribute",
              "ConstructorArguments": [
                "Input"
              ]
            },
            {
              "FullName": "IconAttribute",
              "ConstructorArguments": [
                "gamepad"
              ]
            },
            {
              "FullName": "DescriptionAttribute",
              "ConstructorArguments": [
                "Analog move value from the default input device."
              ]
            },
            {
              "FullName": "Sandbox.Internal.SourceLocationAttribute",
              "ConstructorArguments": [
                "Systems\\Input\\Input.cs",
                "59"
              ]
            }
          ],
          "Documentation": {
            "Summary": "Analog move value from the default input device."
          },
          "DocId": "P:Sandbox.Input.AnalogMove"
        },
        {
          "PropertyType": "Sandbox.InputMotionData",
          "Loc": {
            "File": "Systems/Input/Input.cs",
            "Line": 140
          },
          "IsPublic": true,
          "IsStatic": true,
          "FullName": "Sandbox.Input.MotionData",
          "Name": "MotionData",
          "Attributes": [
            {
              "FullName": "DescriptionAttribute",
              "ConstructorArguments": [
                "Current state of the current input device's motion sensor(s) if supported. This is only supported on: Dualshock 4+, Switch Controllers, Steam Controller, Steam Deck."
              ]
            },
            {
              "FullName": "Sandbox.Internal.SourceLocationAttribute",
              "ConstructorArguments": [
                "Systems\\Input\\Input.cs",
                "139"
              ]
            }
          ],
          "Documentation": {
            "Summary": "Current state of the current input device's motion sensor(s) if supported.\nThis is only supported on: Dualshock 4+, Switch Controllers, Steam Controller, Steam Deck."
          },
          "DocId": "P:Sandbox.Input.MotionData"
        }
      ],
      "IsClass": true,
      "IsAbstract": true,
      "IsSealed": true,
      "Group": "class",
      "Assembly": "Sandbox.Engine",
      "IsPublic": true,
      "IsStatic": true,
      "FullName": "Sandbox.Input",
      "Name": "Input",
      "Attributes": [
        {
          "FullName": "DescriptionAttribute",
          "ConstructorArguments": [
            "Allows querying of player button presses and other inputs."
          ]
        },
        {
          "FullName": "Sandbox.Internal.SourceLocationAttribute",
          "ConstructorArguments": [
            "Systems\\Input\\Controller\\Input.Controller.cs",
            "5"
          ]
        },
        {
          "FullName": "DescriptionAttribute",
          "ConstructorArguments": [
            "Allows querying of player button presses and other inputs."
          ]
        },
        {
          "FullName": "Sandbox.Internal.SourceLocationAttribute",
          "ConstructorArguments": [
            "Systems\\Input\\Input.Actions.cs",
            "6"
          ]
        },
        {
          "FullName": "DescriptionAttribute",
          "ConstructorArguments": [
            "Allows querying of player button presses and other inputs."
          ]
        },
        {
          "FullName": "Sandbox.Internal.SourceLocationAttribute",
          "ConstructorArguments": [
            "Systems\\Input\\Input.Context.cs",
            "6"
          ]
        },
        {
          "FullName": "DescriptionAttribute",
          "ConstructorArguments": [
            "Allows querying of player button presses and other inputs."
          ]
        },
        {
          "FullName": "Sandbox.Internal.SourceLocationAttribute",
          "ConstructorArguments": [
            "Systems\\Input\\Input.cs",
            "9"
          ]
        },
        {
          "FullName": "DescriptionAttribute",
          "ConstructorArguments": [
            "Allows querying of player button presses and other inputs."
          ]
        },
        {
          "FullName": "Sandbox.Internal.SourceLocationAttribute",
          "ConstructorArguments": [
            "Systems\\Input\\Input.Glyphs.cs",
            "3"
          ]
        },
        {
          "FullName": "DescriptionAttribute",
          "ConstructorArguments": [
            "Allows querying of player button presses and other inputs."
          ]
        },
        {
          "FullName": "Sandbox.Internal.SourceLocationAttribute",
          "ConstructorArguments": [
            "Systems\\Input\\Input.Haptics.cs",
            "3"
          ]
        },
        {
          "FullName": "DescriptionAttribute",
          "ConstructorArguments": [
            "Allows querying of player button presses and other inputs."
          ]
        },
        {
          "FullName": "Sandbox.Internal.SourceLocationAttribute",
          "ConstructorArguments": [
            "Systems\\Input\\Input.Keyboard.cs",
            "5"
          ]
        }
      ],
      "Documentation": {
        "Summary": "Allows querying of player button presses and other inputs."
      },
      "DocId": "T:Sandbox.Input"
    },
    {
      "Namespace": "",
      "Methods": [
        {
          "ReturnType": "Sandbox.Texture",
          "Parameters": [
            {
              "Name": "key",
              "Type": "System.String"
            },
            {
              "Name": "size",
              "Type": "Sandbox.InputGlyphSize",
              "Default": "0"
            },
            {
              "Name": "outline",
              "Type": "System.Boolean",
              "Default": "False"
            }
          ],
          "l": {
            "File": "Systems/Input/Input.Glyphs.cs",
            "Line": 157
          },
          "IsPublic": true,
          "IsStatic": true,
          "FullName": "Sandbox.Input.Keyboard.GetGlyph",
          "Name": "GetGlyph",
          "DeclaringType": "Sandbox.Input.Keyboard",
          "Attributes": [
            {
              "FullName": "DescriptionAttribute",
              "ConstructorArguments": [
                "Get a glyph texture from a specific key name."
              ]
            },
            {
              "FullName": "Sandbox.Internal.SourceLocationAttribute",
              "ConstructorArguments": [
                "Systems\\Input\\Input.Glyphs.cs",
                "154"
              ]
            }
          ],
          "Documentation": {
            "Summary": "Get a glyph texture from a specific key name.",
            "Return": "",
            "Params": {
              "key": "",
              "size": "",
              "outline": ""
            }
          },
          "DocId": "M:Sandbox.Input.Keyboard.GetGlyph(System.String,Sandbox.InputGlyphSize,System.Boolean)"
        },
        {
          "ReturnType": "System.Boolean",
          "Parameters": [
            {
              "Name": "keyName",
              "Type": "System.String"
            }
          ],
          "l": {
            "File": "Systems/Input/Input.Keyboard.cs",
            "Line": 15
          },
          "IsPublic": true,
          "IsStatic": true,
          "FullName": "Sandbox.Input.Keyboard.Down",
          "Name": "Down",
          "DeclaringType": "Sandbox.Input.Keyboard",
          "Attributes": [
            {
              "FullName": "DescriptionAttribute",
              "ConstructorArguments": [
                "Keyboard key is held down"
              ]
            },
            {
              "FullName": "Sandbox.Internal.SourceLocationAttribute",
              "ConstructorArguments": [
                "Systems\\Input\\Input.Keyboard.cs",
                "12"
              ]
            }
          ],
          "Documentation": {
            "Summary": "Keyboard key is held down"
          },
          "DocId": "M:Sandbox.Input.Keyboard.Down(System.String)"
        },
        {
          "ReturnType": "System.Boolean",
          "Parameters": [
            {
              "Name": "keyName",
              "Type": "System.String"
            }
          ],
          "l": {
            "File": "Systems/Input/Input.Keyboard.cs",
            "Line": 29
          },
          "IsPublic": true,
          "IsStatic": true,
          "FullName": "Sandbox.Input.Keyboard.Pressed",
          "Name": "Pressed",
          "DeclaringType": "Sandbox.Input.Keyboard",
          "Attributes": [
            {
              "FullName": "DescriptionAttribute",
              "ConstructorArguments": [
                "Keyboard key wasn't pressed but now it is"
              ]
            },
            {
              "FullName": "Sandbox.Internal.SourceLocationAttribute",
              "ConstructorArguments": [
                "Systems\\Input\\Input.Keyboard.cs",
                "26"
              ]
            }
          ],
          "Documentation": {
            "Summary": "Keyboard key wasn't pressed but now it is"
          },
          "DocId": "M:Sandbox.Input.Keyboard.Pressed(System.String)"
        },
        {
          "ReturnType": "System.Boolean",
          "Parameters": [
            {
              "Name": "keyName",
              "Type": "System.String"
            }
          ],
          "l": {
            "File": "Systems/Input/Input.Keyboard.cs",
            "Line": 43
          },
          "IsPublic": true,
          "IsStatic": true,
          "FullName": "Sandbox.Input.Keyboard.Released",
          "Name": "Released",
          "DeclaringType": "Sandbox.Input.Keyboard",
          "Attributes": [
            {
              "FullName": "DescriptionAttribute",
              "ConstructorArguments": [
                "Keyboard key was pressed but now it isn't"
              ]
            },
            {
              "FullName": "Sandbox.Internal.SourceLocationAttribute",
              "ConstructorArguments": [
                "Systems\\Input\\Input.Keyboard.cs",
                "40"
              ]
            }
          ],
          "Documentation": {
            "Summary": "Keyboard key was pressed but now it isn't"
          },
          "DocId": "M:Sandbox.Input.Keyboard.Released(System.String)"
        }
      ],
      "IsClass": true,
      "IsAbstract": true,
      "IsSealed": true,
      "Group": "class",
      "Assembly": "Sandbox.Engine",
      "IsPublic": true,
      "IsStatic": true,
      "FullName": "Sandbox.Input.Keyboard",
      "Name": "Keyboard",
      "DeclaringType": "Sandbox.Input",
      "Attributes": [
        {
          "FullName": "DescriptionAttribute",
          "ConstructorArguments": [
            "Keyboard related glyph methods."
          ]
        },
        {
          "FullName": "Sandbox.Internal.SourceLocationAttribute",
          "ConstructorArguments": [
            "Systems\\Input\\Input.Glyphs.cs",
            "145"
          ]
        },
        {
          "FullName": "DescriptionAttribute",
          "ConstructorArguments": [
            "Keyboard related glyph methods."
          ]
        },
        {
          "FullName": "Sandbox.Internal.SourceLocationAttribute",
          "ConstructorArguments": [
            "Systems\\Input\\Input.Keyboard.cs",
            "7"
          ]
        }
      ],
      "Documentation": {
        "Summary": "Keyboard related glyph methods."
      },
      "DocId": "T:Sandbox.Input.Keyboard"
    }
  ],
  "_metadata": {
    "chunk": 142,
    "items_count": 2
  }
}