{
  "Types": [
    {
      "Namespace": "Sandbox",
      "Methods": [
        {
          "ReturnType": "System.Boolean",
          "Parameters": [
            {
              "Name": "rect",
              "In": true,
              "Type": "Sandbox.Rect"
            },
            {
              "Name": "fullyInside",
              "Type": "System.Boolean",
              "Default": "False"
            }
          ],
          "l": {
            "File": "Math/Rect.cs",
            "Line": 157
          },
          "IsPublic": true,
          "FullName": "Sandbox.Rect.IsInside",
          "Name": "IsInside",
          "DeclaringType": "Sandbox.Rect",
          "Attributes": [
            {
              "FullName": "System.Runtime.CompilerServices.IsReadOnlyAttribute"
            }
          ],
          "Documentation": {
            "Summary": "Return true if the passed rect is partially or fully inside this rect.",
            "Params": {
              "rect": "The passed rect to test.",
              "fullyInside": "<see langword=\"true\" /> to test if the given rect is completely inside this rect. <see langword=\"false\" /> to test for an intersection."
            }
          },
          "DocId": "M:Sandbox.Rect.IsInside(Sandbox.Rect@,System.Boolean)"
        },
        {
          "ReturnType": "System.Boolean",
          "Parameters": [
            {
              "Name": "pos",
              "In": true,
              "Type": "Vector2"
            }
          ],
          "l": {
            "File": "Math/Rect.cs",
            "Line": 175
          },
          "IsPublic": true,
          "FullName": "Sandbox.Rect.IsInside",
          "Name": "IsInside",
          "DeclaringType": "Sandbox.Rect",
          "Attributes": [
            {
              "FullName": "System.Runtime.CompilerServices.IsReadOnlyAttribute"
            }
          ],
          "Documentation": {
            "Summary": "Return true if the passed point is inside this rect."
          },
          "DocId": "M:Sandbox.Rect.IsInside(Vector2@)"
        },
        {
          "ReturnType": "Sandbox.Rect",
          "Parameters": [
            {
              "Name": "left",
              "In": true,
              "Type": "System.Single"
            },
            {
              "Name": "top",
              "In": true,
              "Type": "System.Single"
            },
            {
              "Name": "right",
              "In": true,
              "Type": "System.Single"
            },
            {
              "Name": "bottom",
              "In": true,
              "Type": "System.Single"
            }
          ],
          "l": {
            "File": "Math/Rect.cs",
            "Line": 188
          },
          "IsPublic": true,
          "FullName": "Sandbox.Rect.Shrink",
          "Name": "Shrink",
          "DeclaringType": "Sandbox.Rect",
          "Attributes": [
            {
              "FullName": "System.Runtime.CompilerServices.IsReadOnlyAttribute"
            }
          ],
          "Documentation": {
            "Summary": "Returns a Rect shrunk in every direction by given values."
          },
          "DocId": "M:Sandbox.Rect.Shrink(System.Single@,System.Single@,System.Single@,System.Single@)"
        },
        {
          "ReturnType": "Sandbox.Rect",
          "Parameters": [
            {
              "Name": "m",
              "In": true,
              "Type": "Sandbox.UI.Margin"
            }
          ],
          "l": {
            "File": "Math/Rect.cs",
            "Line": 200
          },
          "IsPublic": true,
          "FullName": "Sandbox.Rect.Shrink",
          "Name": "Shrink",
          "DeclaringType": "Sandbox.Rect",
          "Attributes": [
            {
              "FullName": "System.Runtime.CompilerServices.IsReadOnlyAttribute"
            }
          ],
          "Documentation": {
            "Summary": "Returns a Rect shrunk in every direction by <see cref=\"T:Sandbox.UI.Margin\">Margin</see>'s values."
          },
          "DocId": "M:Sandbox.Rect.Shrink(Sandbox.UI.Margin@)"
        },
        {
          "ReturnType": "Sandbox.Rect",
          "Parameters": [
            {
              "Name": "x",
              "In": true,
              "Type": "System.Single"
            },
            {
              "Name": "y",
              "In": true,
              "Type": "System.Single"
            }
          ],
          "l": {
            "File": "Math/Rect.cs",
            "Line": 205
          },
          "IsPublic": true,
          "FullName": "Sandbox.Rect.Shrink",
          "Name": "Shrink",
          "DeclaringType": "Sandbox.Rect",
          "Attributes": [
            {
              "FullName": "System.Runtime.CompilerServices.IsReadOnlyAttribute"
            }
          ],
          "Documentation": {
            "Summary": "Returns a Rect shrunk in every direction by given values on each axis."
          },
          "DocId": "M:Sandbox.Rect.Shrink(System.Single@,System.Single@)"
        },
        {
          "ReturnType": "Sandbox.Rect",
          "Parameters": [
            {
              "Name": "amt",
              "In": true,
              "Type": "System.Single"
            }
          ],
          "l": {
            "File": "Math/Rect.cs",
            "Line": 210
          },
          "IsPublic": true,
          "FullName": "Sandbox.Rect.Shrink",
          "Name": "Shrink",
          "DeclaringType": "Sandbox.Rect",
          "Attributes": [
            {
              "FullName": "System.Runtime.CompilerServices.IsReadOnlyAttribute"
            }
          ],
          "Documentation": {
            "Summary": "Returns a Rect shrunk in every direction by given amount."
          },
          "DocId": "M:Sandbox.Rect.Shrink(System.Single@)"
        },
        {
          "ReturnType": "Sandbox.Rect",
          "Parameters": [
            {
              "Name": "left",
              "In": true,
              "Type": "System.Single"
            },
            {
              "Name": "top",
              "In": true,
              "Type": "System.Single"
            },
            {
              "Name": "right",
              "In": true,
              "Type": "System.Single"
            },
            {
              "Name": "bottom",
              "In": true,
              "Type": "System.Single"
            }
          ],
          "l": {
            "File": "Math/Rect.cs",
            "Line": 217
          },
          "IsPublic": true,
          "FullName": "Sandbox.Rect.Grow",
          "Name": "Grow",
          "DeclaringType": "Sandbox.Rect",
          "Attributes": [
            {
              "FullName": "System.Runtime.CompilerServices.IsReadOnlyAttribute"
            }
          ],
          "Documentation": {
            "Summary": "Returns a Rect grown in every direction by given amounts."
          },
          "DocId": "M:Sandbox.Rect.Grow(System.Single@,System.Single@,System.Single@,System.Single@)"
        },
        {
          "ReturnType": "Sandbox.Rect",
          "Parameters": [
            {
              "Name": "m",
              "Type": "Sandbox.UI.Margin"
            }
          ],
          "l": {
            "File": "Math/Rect.cs",
            "Line": 229
          },
          "IsPublic": true,
          "FullName": "Sandbox.Rect.Grow",
          "Name": "Grow",
          "DeclaringType": "Sandbox.Rect",
          "Attributes": [
            {
              "FullName": "System.Runtime.CompilerServices.IsReadOnlyAttribute"
            }
          ],
          "Documentation": {
            "Summary": "Returns a Rect grown in every direction by <see cref=\"T:Sandbox.UI.Margin\">Margin</see>'s values."
          },
          "DocId": "M:Sandbox.Rect.Grow(Sandbox.UI.Margin)"
        },
        {
          "ReturnType": "Sandbox.Rect",
          "Parameters": [
            {
              "Name": "x",
              "In": true,
              "Type": "System.Single"
            },
            {
              "Name": "y",
              "In": true,
              "Type": "System.Single"
            }
          ],
          "l": {
            "File": "Math/Rect.cs",
            "Line": 234
          },
          "IsPublic": true,
          "FullName": "Sandbox.Rect.Grow",
          "Name": "Grow",
          "DeclaringType": "Sandbox.Rect",
          "Attributes": [
            {
              "FullName": "System.Runtime.CompilerServices.IsReadOnlyAttribute"
            }
          ],
          "Documentation": {
            "Summary": "Returns a Rect grown in every direction by given values on each axis."
          },
          "DocId": "M:Sandbox.Rect.Grow(System.Single@,System.Single@)"
        },
        {
          "ReturnType": "Sandbox.Rect",
          "Parameters": [
            {
              "Name": "amt",
              "In": true,
              "Type": "System.Single"
            }
          ],
          "l": {
            "File": "Math/Rect.cs",
            "Line": 239
          },
          "IsPublic": true,
          "FullName": "Sandbox.Rect.Grow",
          "Name": "Grow",
          "DeclaringType": "Sandbox.Rect",
          "Attributes": [
            {
              "FullName": "System.Runtime.CompilerServices.IsReadOnlyAttribute"
            }
          ],
          "Documentation": {
            "Summary": "Returns a Rect grown in every direction by given amount."
          },
          "DocId": "M:Sandbox.Rect.Grow(System.Single@)"
        },
        {
          "ReturnType": "Sandbox.Rect",
          "Parameters": [],
          "l": {
            "File": "Math/Rect.cs",
            "Line": 246
          },
          "IsPublic": true,
          "FullName": "Sandbox.Rect.Floor",
          "Name": "Floor",
          "DeclaringType": "Sandbox.Rect",
          "Attributes": [
            {
              "FullName": "System.Runtime.CompilerServices.IsReadOnlyAttribute"
            }
          ],
          "Documentation": {
            "Summary": "Returns a Rect with position and size rounded down."
          },
          "DocId": "M:Sandbox.Rect.Floor"
        },
        {
          "ReturnType": "Sandbox.Rect",
          "Parameters": [],
          "l": {
            "File": "Math/Rect.cs",
            "Line": 259
          },
          "IsPublic": true,
          "FullName": "Sandbox.Rect.Round",
          "Name": "Round",
          "DeclaringType": "Sandbox.Rect",
          "Attributes": [
            {
              "FullName": "System.Runtime.CompilerServices.IsReadOnlyAttribute"
            }
          ],
          "Documentation": {
            "Summary": "Returns a Rect with position and size rounded to closest integer values."
          },
          "DocId": "M:Sandbox.Rect.Round"
        },
        {
          "ReturnType": "Sandbox.Rect",
          "Parameters": [],
          "l": {
            "File": "Math/Rect.cs",
            "Line": 272
          },
          "IsPublic": true,
          "FullName": "Sandbox.Rect.Ceiling",
          "Name": "Ceiling",
          "DeclaringType": "Sandbox.Rect",
          "Attributes": [
            {
              "FullName": "System.Runtime.CompilerServices.IsReadOnlyAttribute"
            }
          ],
          "Documentation": {
            "Summary": "Returns a Rect with position and size rounded up."
          },
          "DocId": "M:Sandbox.Rect.Ceiling"
        },
        {
          "ReturnType": "Sandbox.Rect",
          "Parameters": [
            {
              "Name": "a",
              "In": true,
              "Type": "Vector2"
            },
            {
              "Name": "b",
              "In": true,
              "Type": "Vector2"
            }
          ],
          "l": {
            "File": "Math/Rect.cs",
            "Line": 300
          },
          "IsPublic": true,
          "IsStatic": true,
          "FullName": "Sandbox.Rect.FromPoints",
          "Name": "FromPoints",
          "DeclaringType": "Sandbox.Rect",
          "Documentation": {
            "Summary": "Create a rect between two points. The order of the points doesn't matter."
          },
          "DocId": "M:Sandbox.Rect.FromPoints(Vector2@,Vector2@)"
        },
        {
          "ReturnType": "Vector4",
          "Parameters": [],
          "l": {
            "File": "Math/Rect.cs",
            "Line": 313
          },
          "IsPublic": true,
          "FullName": "Sandbox.Rect.ToVector4",
          "Name": "ToVector4",
          "DeclaringType": "Sandbox.Rect",
          "Attributes": [
            {
              "FullName": "System.Runtime.CompilerServices.IsReadOnlyAttribute"
            }
          ],
          "Documentation": {
            "Summary": "Returns this rect as a Vector4, where X/Y/Z/W are Left/Top/Right/Bottom respectively.",
            "Return": ""
          },
          "DocId": "M:Sandbox.Rect.ToVector4"
        },
        {
          "ReturnType": "System.Void",
          "Parameters": [
            {
              "Name": "r",
              "Type": "Sandbox.Rect"
            }
          ],
          "l": {
            "File": "Math/Rect.cs",
            "Line": 321
          },
          "IsPublic": true,
          "FullName": "Sandbox.Rect.Add",
          "Name": "Add",
          "DeclaringType": "Sandbox.Rect",
          "Documentation": {
            "Summary": "Expand this Rect to contain the other rect"
          },
          "DocId": "M:Sandbox.Rect.Add(Sandbox.Rect)"
        },
        {
          "ReturnType": "System.Void",
          "Parameters": [
            {
              "Name": "point",
              "Type": "Vector2"
            }
          ],
          "l": {
            "File": "Math/Rect.cs",
            "Line": 332
          },
          "IsPublic": true,
          "FullName": "Sandbox.Rect.Add",
          "Name": "Add",
          "DeclaringType": "Sandbox.Rect",
          "Documentation": {
            "Summary": "Expand this Rect to contain the point"
          },
          "DocId": "M:Sandbox.Rect.Add(Vector2)"
        },
        {
          "ReturnType": "Sandbox.Rect",
          "Parameters": [
            {
              "Name": "pos",
              "Type": "Vector2"
            }
          ],
          "l": {
            "File": "Math/Rect.cs",
            "Line": 343
          },
          "IsPublic": true,
          "FullName": "Sandbox.Rect.AddPoint",
          "Name": "AddPoint",
          "DeclaringType": "Sandbox.Rect",
          "Attributes": [
            {
              "FullName": "System.Runtime.CompilerServices.IsReadOnlyAttribute"
            }
          ],
          "Documentation": {
            "Summary": "Returns this rect expanded to include this point"
          },
          "DocId": "M:Sandbox.Rect.AddPoint(Vector2)"
        },
        {
          "ReturnType": "Vector2",
          "Parameters": [
            {
              "Name": "point",
              "In": true,
              "Type": "Vector2"
            }
          ],
          "l": {
            "File": "Math/Rect.cs",
            "Line": 354
          },
          "IsPublic": true,
          "FullName": "Sandbox.Rect.ClosestPoint",
          "Name": "ClosestPoint",
          "DeclaringType": "Sandbox.Rect",
          "Attributes": [
            {
              "FullName": "System.Runtime.CompilerServices.IsReadOnlyAttribute"
            }
          ],
          "Documentation": {
            "Summary": "Returns the closest point on this rect to another point"
          },
          "DocId": "M:Sandbox.Rect.ClosestPoint(Vector2@)"
        },
        {
          "ReturnType": "Sandbox.Rect",
          "Parameters": [
            {
              "Name": "size",
              "In": true,
              "Type": "Vector2"
            },
            {
              "Name": "align",
              "Type": "Sandbox.TextFlag"
            }
          ],
          "l": {
            "File": "Math/Rect.cs",
            "Line": 396
          },
          "IsPublic": true,
          "FullName": "Sandbox.Rect.Align",
          "Name": "Align",
          "DeclaringType": "Sandbox.Rect",
          "Attributes": [
            {
              "FullName": "System.Runtime.CompilerServices.IsReadOnlyAttribute"
            }
          ],
          "Documentation": {
            "Summary": "Align the smaller rect inside this rect.\nDefault alignment on each axis is Top, Left."
          },
          "DocId": "M:Sandbox.Rect.Align(Vector2@,Sandbox.TextFlag)"
        },
        {
          "ReturnType": "Sandbox.Rect",
          "Parameters": [],
          "l": {
            "File": "Math/Rect.cs",
            "Line": 431
          },
          "IsPublic": true,
          "FullName": "Sandbox.Rect.SnapToGrid",
          "Name": "SnapToGrid",
          "DeclaringType": "Sandbox.Rect",
          "Attributes": [
            {
              "FullName": "System.Runtime.CompilerServices.IsReadOnlyAttribute"
            }
          ],
          "Documentation": {
            "Summary": "Align to a grid"
          },
          "DocId": "M:Sandbox.Rect.SnapToGrid"
        },
        {
          "ReturnType": "Sandbox.Rect",
          "Parameters": [
            {
              "Name": "size",
              "In": true,
              "Type": "Vector2"
            },
            {
              "Name": "align",
              "Type": "Sandbox.TextFlag",
              "Default": "132"
            },
            {
              "Name": "stretch",
              "Type": "System.Boolean",
              "Default": "False"
            }
          ],
          "l": {
            "File": "Math/Rect.cs",
            "Line": 450
          },
          "IsPublic": true,
          "FullName": "Sandbox.Rect.Contain",
          "Name": "Contain",
          "DeclaringType": "Sandbox.Rect",
          "Documentation": {
            "Summary": "Contain a given rectangle (image) within this rectangle (frame), preserving aspect ratio.",
            "Return": "A rectangle with correct position and size to fit within the \"parent\" rectangle.",
            "Params": {
              "size": "Size of the rectagle (image) to try to contain within this frame rectangle.",
              "align": "Where to align the given box within this rectangle.",
              "stretch": "Whether to stretch the given rectagle (image) should its size be smaller than largest rectagle (image) size possible within this rectangle (frame)."
            }
          },
          "DocId": "M:Sandbox.Rect.Contain(Vector2@,Sandbox.TextFlag,System.Boolean)"
        }
      ],
      "Constructors": [
        {
          "ReturnType": "System.Void",
          "Parameters": [
            {
              "Name": "x",
              "In": true,
              "Type": "System.Single"
            },
            {
              "Name": "y",
              "In": true,
              "Type": "System.Single"
            },
            {
              "Name": "width",
              "In": true,
              "Type": "System.Single"
            },
            {
              "Name": "height",
              "In": true,
              "Type": "System.Single"
            }
          ],
          "l": {
            "File": "Math/Rect.cs",
            "Line": 24
          },
          "IsPublic": true,
          "FullName": "Sandbox.Rect..ctor",
          "Name": ".ctor",
          "DeclaringType": "Sandbox.Rect",
          "Documentation": {
            "Summary": "Initialize a Rect at given position and with given size."
          },
          "DocId": "M:Sandbox.Rect.#ctor(System.Single@,System.Single@,System.Single@,System.Single@)"
        },
        {
          "ReturnType": "System.Void",
          "Parameters": [
            {
              "Name": "point",
              "In": true,
              "Type": "Vector2"
            },
            {
              "Name": "size",
              "In": true,
              "Type": "Vector2",
              "Default": "null"
            }
          ],
          "l": {
            "File": "Math/Rect.cs",
            "Line": 35
          },
          "IsPublic": true,
          "FullName": "Sandbox.Rect..ctor",
          "Name": ".ctor",
          "DeclaringType": "Sandbox.Rect",
          "Documentation": {
            "Summary": "Initialize a Rect at given position and with given size."
          },
          "DocId": "M:Sandbox.Rect.#ctor(Vector2@,Vector2@)"
        }
      ],
      "Properties": [
        {
          "PropertyType": "System.Single",
          "Loc": {
            "File": "Math/Rect.cs",
            "Line": 48
          },
          "IsPublic": true,
          "FullName": "Sandbox.Rect.Width",
          "Name": "Width",
          "Attributes": [
            {
              "FullName": "System.Text.Json.Serialization.JsonIgnoreAttribute"
            },
            {
              "FullName": "Sandbox.HideAttribute"
            }
          ],
          "Documentation": {
            "Summary": "Width of the rect."
          },
          "DocId": "P:Sandbox.Rect.Width"
        },
        {
          "PropertyType": "System.Single",
          "Loc": {
            "File": "Math/Rect.cs",
            "Line": 58
          },
          "IsPublic": true,
          "FullName": "Sandbox.Rect.Height",
          "Name": "Height",
          "Attributes": [
            {
              "FullName": "System.Text.Json.Serialization.JsonIgnoreAttribute"
            },
            {
              "FullName": "Sandbox.HideAttribute"
            }
          ],
          "Documentation": {
            "Summary": "Height of the rect."
          },
          "DocId": "P:Sandbox.Rect.Height"
        },
        {
          "PropertyType": "System.Single",
          "Loc": {
            "File": "Math/Rect.cs",
            "Line": 68
          },
          "IsPublic": true,
          "FullName": "Sandbox.Rect.Left",
          "Name": "Left",
          "Attributes": [
            {
              "FullName": "System.Text.Json.Serialization.JsonIgnoreAttribute"
            },
            {
              "FullName": "Sandbox.HideAttribute"
            }
          ],
          "Documentation": {
            "Summary": "Position of rect's left edge relative to its parent, can also be interpreted as its position on the X axis."
          },
          "DocId": "P:Sandbox.Rect.Left"
        },
        {
          "PropertyType": "System.Single",
          "Loc": {
            "File": "Math/Rect.cs",
            "Line": 78
          },
          "IsPublic": true,
          "FullName": "Sandbox.Rect.Top",
          "Name": "Top",
          "Attributes": [
            {
              "FullName": "System.Text.Json.Serialization.JsonIgnoreAttribute"
            },
            {
              "FullName": "Sandbox.HideAttribute"
            }
          ],
          "Documentation": {
            "Summary": "Position of rect's top edge relative to its parent, can also be interpreted as its position on the Y axis."
          },
          "DocId": "P:Sandbox.Rect.Top"
        },
        {
          "PropertyType": "System.Single",
          "Loc": {
            "File": "Math/Rect.cs",
            "Line": 88
          },
          "IsPublic": true,
          "FullName": "Sandbox.Rect.Right",
          "Name": "Right",
          "Attributes": [
            {
              "FullName": "System.Text.Json.Serialization.JsonIgnoreAttribute"
            },
            {
              "FullName": "Sandbox.HideAttribute"
            }
          ],
          "Documentation": {
            "Summary": "Position of rect's right edge relative to its parent."
          },
          "DocId": "P:Sandbox.Rect.Right"
        },
        {
          "PropertyType": "System.Single",
          "Loc": {
            "File": "Math/Rect.cs",
            "Line": 98
          },
          "IsPublic": true,
          "FullName": "Sandbox.Rect.Bottom",
          "Name": "Bottom",
          "Attributes": [
            {
              "FullName": "System.Text.Json.Serialization.JsonIgnoreAttribute"
            },
            {
              "FullName": "Sandbox.HideAttribute"
            }
          ],
          "Documentation": {
            "Summary": "Position of rect's bottom edge relative to its parent."
          },
          "DocId": "P:Sandbox.Rect.Bottom"
        },
        {
          "PropertyType": "Vector2",
          "Loc": {
            "File": "Math/Rect.cs",
            "Line": 109
          },
          "IsPublic": true,
          "FullName": "Sandbox.Rect.Position",
          "Name": "Position",
          "Documentation": {
            "Summary": "Position of this rect."
          },
          "DocId": "P:Sandbox.Rect.Position"
        },
        {
          "PropertyType": "Vector2",
          "Loc": {
            "File": "Math/Rect.cs",
            "Line": 122
          },
          "IsPublic": true,
          "FullName": "Sandbox.Rect.Center",
          "Name": "Center",
          "Attributes": [
            {
              "FullName": "System.Text.Json.Serialization.JsonIgnoreAttribute"
            },
            {
              "FullName": "Sandbox.HideAttribute"
            }
          ],
          "Documentation": {
            "Summary": "Center of this rect."
          },
          "DocId": "P:Sandbox.Rect.Center"
        },
        {
          "PropertyType": "Vector2",
          "Loc": {
            "File": "Math/Rect.cs",
            "Line": 133
          },
          "IsPublic": true,
          "FullName": "Sandbox.Rect.Size",
          "Name": "Size",
          "Documentation": {
            "Summary": "Size of this rect."
          },
          "DocId": "P:Sandbox.Rect.Size"
        },
        {
          "PropertyType": "Sandbox.Rect",
          "Loc": {
            "File": "Math/Rect.cs",
            "Line": 142
          },
          "IsPublic": true,
          "FullName": "Sandbox.Rect.WithoutPosition",
          "Name": "WithoutPosition",
          "Attributes": [
            {
              "FullName": "System.Text.Json.Serialization.JsonIgnoreAttribute"
            },
            {
              "FullName": "Sandbox.HideAttribute"
            }
          ],
          "Documentation": {
            "Summary": "Returns this rect with position set to 0 on both axes."
          },
          "DocId": "P:Sandbox.Rect.WithoutPosition"
        },
        {
          "PropertyType": "Vector2",
          "Loc": {
            "File": "Math/Rect.cs",
            "Line": 370
          },
          "IsPublic": true,
          "FullName": "Sandbox.Rect.BottomLeft",
          "Name": "BottomLeft",
          "Attributes": [
            {
              "FullName": "System.Text.Json.Serialization.JsonIgnoreAttribute"
            },
            {
              "FullName": "Sandbox.HideAttribute"
            }
          ],
          "Documentation": {
            "Summary": "Position of the bottom left edge of this rect."
          },
          "DocId": "P:Sandbox.Rect.BottomLeft"
        },
        {
          "PropertyType": "Vector2",
          "Loc": {
            "File": "Math/Rect.cs",
            "Line": 376
          },
          "IsPublic": true,
          "FullName": "Sandbox.Rect.BottomRight",
          "Name": "BottomRight",
          "Attributes": [
            {
              "FullName": "System.Text.Json.Serialization.JsonIgnoreAttribute"
            },
            {
              "FullName": "Sandbox.HideAttribute"
            }
          ],
          "Documentation": {
            "Summary": "Position of the bottom right edge of this rect."
          },
          "DocId": "P:Sandbox.Rect.BottomRight"
        },
        {
          "PropertyType": "Vector2",
          "Loc": {
            "File": "Math/Rect.cs",
            "Line": 382
          },
          "IsPublic": true,
          "FullName": "Sandbox.Rect.TopRight",
          "Name": "TopRight",
          "Attributes": [
            {
              "FullName": "System.Text.Json.Serialization.JsonIgnoreAttribute"
            },
            {
              "FullName": "Sandbox.HideAttribute"
            }
          ],
          "Documentation": {
            "Summary": "Position of the top right edge of this rect."
          },
          "DocId": "P:Sandbox.Rect.TopRight"
        },
        {
          "PropertyType": "Vector2",
          "Loc": {
            "File": "Math/Rect.cs",
            "Line": 388
          },
          "IsPublic": true,
          "FullName": "Sandbox.Rect.TopLeft",
          "Name": "TopLeft",
          "Attributes": [
            {
              "FullName": "System.Text.Json.Serialization.JsonIgnoreAttribute"
            },
            {
              "FullName": "Sandbox.HideAttribute"
            }
          ],
          "Documentation": {
            "Summary": "Position of the top left edge of this rect."
          },
          "DocId": "P:Sandbox.Rect.TopLeft"
        }
      ],
      "IsClass": true,
      "IsSealed": true,
      "IsValueType": true,
      "Group": "struct",
      "Assembly": "Sandbox.System",
      "IsPublic": true,
      "FullName": "Sandbox.Rect",
      "Name": "Rect",
      "Documentation": {
        "Summary": "Represents a rectangle."
      },
      "DocId": "T:Sandbox.Rect"
    },
    {
      "Namespace": "Sandbox",
      "Methods": [
        {
          "ReturnType": "System.Boolean",
          "Parameters": [
            {
              "Name": "rect",
              "In": true,
              "Type": "Sandbox.RectInt"
            },
            {
              "Name": "fullyInside",
              "Type": "System.Boolean",
              "Default": "False"
            }
          ],
          "l": {
            "File": "Math/RectInt.cs",
            "Line": 157
          },
          "IsPublic": true,
          "FullName": "Sandbox.RectInt.IsInside",
          "Name": "IsInside",
          "DeclaringType": "Sandbox.RectInt",
          "Attributes": [
            {
              "FullName": "System.Runtime.CompilerServices.IsReadOnlyAttribute"
            }
          ],
          "Documentation": {
            "Summary": "Return true if the passed rect is partially or fully inside this rect.",
            "Params": {
              "rect": "The passed rect to test.",
              "fullyInside": "<see langword=\"true\" /> to test if the given rect is completely inside this rect. <see langword=\"false\" /> to test for an intersection."
            }
          },
          "DocId": "M:Sandbox.RectInt.IsInside(Sandbox.RectInt@,System.Boolean)"
        },
        {
          "ReturnType": "System.Boolean",
          "Parameters": [
            {
              "Name": "pos",
              "In": true,
              "Type": "Vector2Int"
            }
          ],
          "l": {
            "File": "Math/RectInt.cs",
            "Line": 175
          },
          "IsPublic": true,
          "FullName": "Sandbox.RectInt.IsInside",
          "Name": "IsInside",
          "DeclaringType": "Sandbox.RectInt",
          "Attributes": [
            {
              "FullName": "System.Runtime.CompilerServices.IsReadOnlyAttribute"
            }
          ],
          "Documentation": {
            "Summary": "Return true if the passed point is inside this rect."
          },
          "DocId": "M:Sandbox.RectInt.IsInside(Vector2Int@)"
        },
        {
          "ReturnType": "Sandbox.RectInt",
          "Parameters": [
            {
              "Name": "left",
              "In": true,
              "Type": "System.Int32"
            },
            {
              "Name": "top",
              "In": true,
              "Type": "System.Int32"
            },
            {
              "Name": "right",
              "In": true,
              "Type": "System.Int32"
            },
            {
              "Name": "bottom",
              "In": true,
              "Type": "System.Int32"
            }
          ],
          "l": {
            "File": "Math/RectInt.cs",
            "Line": 188
          },
          "IsPublic": true,
          "FullName": "Sandbox.RectInt.Shrink",
          "Name": "Shrink",
          "DeclaringType": "Sandbox.RectInt",
          "Attributes": [
            {
              "FullName": "System.Runtime.CompilerServices.IsReadOnlyAttribute"
            }
          ],
          "Documentation": {
            "Summary": "Returns a Rect shrunk in every direction by given values."
          },
          "DocId": "M:Sandbox.RectInt.Shrink(System.Int32@,System.Int32@,System.Int32@,System.Int32@)"
        },
        {
          "ReturnType": "Sandbox.RectInt",
          "Parameters": [
            {
              "Name": "x",
              "In": true,
              "Type": "System.Int32"
            },
            {
              "Name": "y",
              "In": true,
              "Type": "System.Int32"
            }
          ],
          "l": {
            "File": "Math/RectInt.cs",
            "Line": 200
          },
          "IsPublic": true,
          "FullName": "Sandbox.RectInt.Shrink",
          "Name": "Shrink",
          "DeclaringType": "Sandbox.RectInt",
          "Attributes": [
            {
              "FullName": "System.Runtime.CompilerServices.IsReadOnlyAttribute"
            }
          ],
          "Documentation": {
            "Summary": "Returns a Rect shrunk in every direction by given values on each axis."
          },
          "DocId": "M:Sandbox.RectInt.Shrink(System.Int32@,System.Int32@)"
        },
        {
          "ReturnType": "Sandbox.RectInt",
          "Parameters": [
            {
              "Name": "amt",
              "In": true,
              "Type": "System.Int32"
            }
          ],
          "l": {
            "File": "Math/RectInt.cs",
            "Line": 205
          },
          "IsPublic": true,
          "FullName": "Sandbox.RectInt.Shrink",
          "Name": "Shrink",
          "DeclaringType": "Sandbox.RectInt",
          "Attributes": [
            {
              "FullName": "System.Runtime.CompilerServices.IsReadOnlyAttribute"
            }
          ],
          "Documentation": {
            "Summary": "Returns a Rect shrunk in every direction by given amount."
          },
          "DocId": "M:Sandbox.RectInt.Shrink(System.Int32@)"
        },
        {
          "ReturnType": "Sandbox.RectInt",
          "Parameters": [
            {
              "Name": "left",
              "In": true,
              "Type": "System.Int32"
            },
            {
              "Name": "top",
              "In": true,
              "Type": "System.Int32"
            },
            {
              "Name": "right",
              "In": true,
              "Type": "System.Int32"
            },
            {
              "Name": "bottom",
              "In": true,
              "Type": "System.Int32"
            }
          ],
          "l": {
            "File": "Math/RectInt.cs",
            "Line": 212
          },
          "IsPublic": true,
          "FullName": "Sandbox.RectInt.Grow",
          "Name": "Grow",
          "DeclaringType": "Sandbox.RectInt",
          "Attributes": [
            {
              "FullName": "System.Runtime.CompilerServices.IsReadOnlyAttribute"
            }
          ],
          "Documentation": {
            "Summary": "Returns a Rect grown in every direction by given amounts."
          },
          "DocId": "M:Sandbox.RectInt.Grow(System.Int32@,System.Int32@,System.Int32@,System.Int32@)"
        },
        {
          "ReturnType": "Sandbox.RectInt",
          "Parameters": [
            {
              "Name": "x",
              "In": true,
              "Type": "System.Int32"
            },
            {
              "Name": "y",
              "In": true,
              "Type": "System.Int32"
            }
          ],
          "l": {
            "File": "Math/RectInt.cs",
            "Line": 224
          },
          "IsPublic": true,
          "FullName": "Sandbox.RectInt.Grow",
          "Name": "Grow",
          "DeclaringType": "Sandbox.RectInt",
          "Attributes": [
            {
              "FullName": "System.Runtime.CompilerServices.IsReadOnlyAttribute"
            }
          ],
          "Documentation": {
            "Summary": "Returns a Rect grown in every direction by given values on each axis."
          },
          "DocId": "M:Sandbox.RectInt.Grow(System.Int32@,System.Int32@)"
        },
        {
          "ReturnType": "Sandbox.RectInt",
          "Parameters": [
            {
              "Name": "amt",
              "In": true,
              "Type": "System.Int32"
            }
          ],
          "l": {
            "File": "Math/RectInt.cs",
            "Line": 229
          },
          "IsPublic": true,
          "FullName": "Sandbox.RectInt.Grow",
          "Name": "Grow",
          "DeclaringType": "Sandbox.RectInt",
          "Attributes": [
            {
              "FullName": "System.Runtime.CompilerServices.IsReadOnlyAttribute"
            }
          ],
          "Documentation": {
            "Summary": "Returns a Rect grown in every direction by given amount."
          },
          "DocId": "M:Sandbox.RectInt.Grow(System.Int32@)"
        },
        {
          "ReturnType": "Sandbox.RectInt",
          "Parameters": [
            {
              "Name": "a",
              "In": true,
              "Type": "Vector2Int"
            },
            {
              "Name": "b",
              "In": true,
              "Type": "Vector2Int"
            }
          ],
          "l": {
            "File": "Math/RectInt.cs",
            "Line": 251
          },
          "IsPublic": true,
          "IsStatic": true,
          "FullName": "Sandbox.RectInt.FromPoints",
          "Name": "FromPoints",
          "DeclaringType": "Sandbox.RectInt",
          "Documentation": {
            "Summary": "Create a rect between two points. The order of the points doesn't matter."
          },
          "DocId": "M:Sandbox.RectInt.FromPoints(Vector2Int@,Vector2Int@)"
        },
        {
          "ReturnType": "System.Void",
          "Parameters": [
            {
              "Name": "r",
              "Type": "Sandbox.RectInt"
            }
          ],
          "l": {
            "File": "Math/RectInt.cs",
            "Line": 263
          },
          "IsPublic": true,
          "FullName": "Sandbox.RectInt.Add",
          "Name": "Add",
          "DeclaringType": "Sandbox.RectInt",
          "Documentation": {
            "Summary": "Expand this Rect to contain the other rect"
          },
          "DocId": "M:Sandbox.RectInt.Add(Sandbox.RectInt)"
        },
        {
          "ReturnType": "System.Void",
          "Parameters": [
            {
              "Name": "point",
              "Type": "Vector2Int"
            }
          ],
          "l": {
            "File": "Math/RectInt.cs",
            "Line": 274
          },
          "IsPublic": true,
          "FullName": "Sandbox.RectInt.Add",
          "Name": "Add",
          "DeclaringType": "Sandbox.RectInt",
          "Documentation": {
            "Summary": "Expand this Rect to contain the point"
          },
          "DocId": "M:Sandbox.RectInt.Add(Vector2Int)"
        },
        {
          "ReturnType": "Sandbox.RectInt",
          "Parameters": [
            {
              "Name": "pos",
              "Type": "Vector2Int"
            }
          ],
          "l": {
            "File": "Math/RectInt.cs",
            "Line": 285
          },
          "IsPublic": true,
          "FullName": "Sandbox.RectInt.AddPoint",
          "Name": "AddPoint",
          "DeclaringType": "Sandbox.RectInt",
          "Attributes": [
            {
              "FullName": "System.Runtime.CompilerServices.IsReadOnlyAttribute"
            }
          ],
          "Documentation": {
            "Summary": "Returns this rect expanded to include this point"
          },
          "DocId": "M:Sandbox.RectInt.AddPoint(Vector2Int)"
        }
      ],
      "Constructors": [
        {
          "ReturnType": "System.Void",
          "Parameters": [
            {
              "Name": "x",
              "In": true,
              "Type": "System.Int32"
            },
            {
              "Name": "y",
              "In": true,
              "Type": "System.Int32"
            },
            {
              "Name": "width",
              "In": true,
              "Type": "System.Int32"
            },
            {
              "Name": "height",
              "In": true,
              "Type": "System.Int32"
            }
          ],
          "l": {
            "File": "Math/RectInt.cs",
            "Line": 24
          },
          "IsPublic": true,
          "FullName": "Sandbox.RectInt..ctor",
          "Name": ".ctor",
          "DeclaringType": "Sandbox.RectInt",
          "Documentation": {
            "Summary": "Initialize a Rect at given position and with given size."
          },
          "DocId": "M:Sandbox.RectInt.#ctor(System.Int32@,System.Int32@,System.Int32@,System.Int32@)"
        },
        {
          "ReturnType": "System.Void",
          "Parameters": [
            {
              "Name": "point",
              "In": true,
              "Type": "Vector2Int"
            },
            {
              "Name": "size",
              "In": true,
              "Type": "Vector2Int",
              "Default": "null"
            }
          ],
          "l": {
            "File": "Math/RectInt.cs",
            "Line": 35
          },
          "IsPublic": true,
          "FullName": "Sandbox.RectInt..ctor",
          "Name": ".ctor",
          "DeclaringType": "Sandbox.RectInt",
          "Documentation": {
            "Summary": "Initialize a Rect at given position and with given size."
          },
          "DocId": "M:Sandbox.RectInt.#ctor(Vector2Int@,Vector2Int@)"
        }
      ],
      "Properties": [
        {
          "PropertyType": "System.Int32",
          "Loc": {
            "File": "Math/RectInt.cs",
            "Line": 48
          },
          "IsPublic": true,
          "FullName": "Sandbox.RectInt.Width",
          "Name": "Width",
          "Attributes": [
            {
              "FullName": "System.Text.Json.Serialization.JsonIgnoreAttribute"
            },
            {
              "FullName": "Sandbox.HideAttribute"
            }
          ],
          "Documentation": {
            "Summary": "Width of the rect."
          },
          "DocId": "P:Sandbox.RectInt.Width"
        },
        {
          "PropertyType": "System.Int32",
          "Loc": {
            "File": "Math/RectInt.cs",
            "Line": 58
          },
          "IsPublic": true,
          "FullName": "Sandbox.RectInt.Height",
          "Name": "Height",
          "Attributes": [
            {
              "FullName": "System.Text.Json.Serialization.JsonIgnoreAttribute"
            },
            {
              "FullName": "Sandbox.HideAttribute"
            }
          ],
          "Documentation": {
            "Summary": "Height of the rect."
          },
          "DocId": "P:Sandbox.RectInt.Height"
        },
        {
          "PropertyType": "System.Int32",
          "Loc": {
            "File": "Math/RectInt.cs",
            "Line": 68
          },
          "IsPublic": true,
          "FullName": "Sandbox.RectInt.Left",
          "Name": "Left",
          "Attributes": [
            {
              "FullName": "System.Text.Json.Serialization.JsonIgnoreAttribute"
            },
            {
              "FullName": "Sandbox.HideAttribute"
            }
          ],
          "Documentation": {
            "Summary": "Position of rect's left edge relative to its parent, can also be interpreted as its position on the X axis."
          },
          "DocId": "P:Sandbox.RectInt.Left"
        },
        {
          "PropertyType": "System.Int32",
          "Loc": {
            "File": "Math/RectInt.cs",
            "Line": 78
          },
          "IsPublic": true,
          "FullName": "Sandbox.RectInt.Top",
          "Name": "Top",
          "Attributes": [
            {
              "FullName": "System.Text.Json.Serialization.JsonIgnoreAttribute"
            },
            {
              "FullName": "Sandbox.HideAttribute"
            }
          ],
          "Documentation": {
            "Summary": "Position of rect's top edge relative to its parent, can also be interpreted as its position on the Y axis."
          },
          "DocId": "P:Sandbox.RectInt.Top"
        },
        {
          "PropertyType": "System.Int32",
          "Loc": {
            "File": "Math/RectInt.cs",
            "Line": 88
          },
          "IsPublic": true,
          "FullName": "Sandbox.RectInt.Right",
          "Name": "Right",
          "Attributes": [
            {
              "FullName": "System.Text.Json.Serialization.JsonIgnoreAttribute"
            },
            {
              "FullName": "Sandbox.HideAttribute"
            }
          ],
          "Documentation": {
            "Summary": "Position of rect's right edge relative to its parent."
          },
          "DocId": "P:Sandbox.RectInt.Right"
        },
        {
          "PropertyType": "System.Int32",
          "Loc": {
            "File": "Math/RectInt.cs",
            "Line": 98
          },
          "IsPublic": true,
          "FullName": "Sandbox.RectInt.Bottom",
          "Name": "Bottom",
          "Attributes": [
            {
              "FullName": "System.Text.Json.Serialization.JsonIgnoreAttribute"
            },
            {
              "FullName": "Sandbox.HideAttribute"
            }
          ],
          "Documentation": {
            "Summary": "Position of rect's bottom edge relative to its parent."
          },
          "DocId": "P:Sandbox.RectInt.Bottom"
        },
        {
          "PropertyType": "Vector2Int",
          "Loc": {
            "File": "Math/RectInt.cs",
            "Line": 109
          },
          "IsPublic": true,
          "FullName": "Sandbox.RectInt.Position",
          "Name": "Position",
          "Documentation": {
            "Summary": "Position of this rect."
          },
          "DocId": "P:Sandbox.RectInt.Position"
        },
        {
          "PropertyType": "Vector2",
          "Loc": {
            "File": "Math/RectInt.cs",
            "Line": 122
          },
          "IsPublic": true,
          "FullName": "Sandbox.RectInt.Center",
          "Name": "Center",
          "Attributes": [
            {
              "FullName": "System.Text.Json.Serialization.JsonIgnoreAttribute"
            },
            {
              "FullName": "Sandbox.HideAttribute"
            }
          ],
          "Documentation": {
            "Summary": "Center of this rect."
          },
          "DocId": "P:Sandbox.RectInt.Center"
        },
        {
          "PropertyType": "Vector2Int",
          "Loc": {
            "File": "Math/RectInt.cs",
            "Line": 133
          },
          "IsPublic": true,
          "FullName": "Sandbox.RectInt.Size",
          "Name": "Size",
          "Documentation": {
            "Summary": "Size of this rect."
          },
          "DocId": "P:Sandbox.RectInt.Size"
        },
        {
          "PropertyType": "Sandbox.RectInt",
          "Loc": {
            "File": "Math/RectInt.cs",
            "Line": 142
          },
          "IsPublic": true,
          "FullName": "Sandbox.RectInt.WithoutPosition",
          "Name": "WithoutPosition",
          "Attributes": [
            {
              "FullName": "System.Text.Json.Serialization.JsonIgnoreAttribute"
            },
            {
              "FullName": "Sandbox.HideAttribute"
            }
          ],
          "Documentation": {
            "Summary": "Returns this rect with position set to 0 on both axes."
          },
          "DocId": "P:Sandbox.RectInt.WithoutPosition"
        },
        {
          "PropertyType": "Vector2Int",
          "Loc": {
            "File": "Math/RectInt.cs",
            "Line": 295
          },
          "IsPublic": true,
          "FullName": "Sandbox.RectInt.BottomLeft",
          "Name": "BottomLeft",
          "Attributes": [
            {
              "FullName": "System.Text.Json.Serialization.JsonIgnoreAttribute"
            },
            {
              "FullName": "Sandbox.HideAttribute"
            }
          ],
          "Documentation": {
            "Summary": "Position of the bottom left edge of this rect."
          },
          "DocId": "P:Sandbox.RectInt.BottomLeft"
        },
        {
          "PropertyType": "Vector2Int",
          "Loc": {
            "File": "Math/RectInt.cs",
            "Line": 301
          },
          "IsPublic": true,
          "FullName": "Sandbox.RectInt.BottomRight",
          "Name": "BottomRight",
          "Attributes": [
            {
              "FullName": "System.Text.Json.Serialization.JsonIgnoreAttribute"
            },
            {
              "FullName": "Sandbox.HideAttribute"
            }
          ],
          "Documentation": {
            "Summary": "Position of the bottom right edge of this rect."
          },
          "DocId": "P:Sandbox.RectInt.BottomRight"
        },
        {
          "PropertyType": "Vector2Int",
          "Loc": {
            "File": "Math/RectInt.cs",
            "Line": 307
          },
          "IsPublic": true,
          "FullName": "Sandbox.RectInt.TopRight",
          "Name": "TopRight",
          "Attributes": [
            {
              "FullName": "System.Text.Json.Serialization.JsonIgnoreAttribute"
            },
            {
              "FullName": "Sandbox.HideAttribute"
            }
          ],
          "Documentation": {
            "Summary": "Position of the top right edge of this rect."
          },
          "DocId": "P:Sandbox.RectInt.TopRight"
        },
        {
          "PropertyType": "Vector2Int",
          "Loc": {
            "File": "Math/RectInt.cs",
            "Line": 313
          },
          "IsPublic": true,
          "FullName": "Sandbox.RectInt.TopLeft",
          "Name": "TopLeft",
          "Attributes": [
            {
              "FullName": "System.Text.Json.Serialization.JsonIgnoreAttribute"
            },
            {
              "FullName": "Sandbox.HideAttribute"
            }
          ],
          "Documentation": {
            "Summary": "Position of the top left edge of this rect."
          },
          "DocId": "P:Sandbox.RectInt.TopLeft"
        }
      ],
      "IsClass": true,
      "IsSealed": true,
      "IsValueType": true,
      "Group": "struct",
      "Assembly": "Sandbox.System",
      "IsPublic": true,
      "FullName": "Sandbox.RectInt",
      "Name": "RectInt",
      "Documentation": {
        "Summary": "Represents a rectangle but with whole numbers"
      },
      "DocId": "T:Sandbox.RectInt"
    }
  ],
  "_metadata": {
    "chunk": 18,
    "items_count": 2
  }
}